{"ranking": "1", "school": "清华大学", "local": "北京", "total": "94.0 ", "index_score": "100.0 "}
{"ranking": "2", "school": "北京大学", "local": "北京", "total": "81.2 ", "index_score": "96.1 "}
{"ranking": "3", "school": "浙江大学", "local": "浙江", "total": "77.8 ", "index_score": "87.2 "}
{"ranking": "4", "school": "上海交通大学", "local": "上海", "total": "77.5 ", "index_score": "89.4 "}
{"ranking": "5", "school": "复旦大学", "local": "上海", "total": "71.1 ", "index_score": "91.8 "}
{"ranking": "6", "school": "中国科学技术大学", "local": "安徽", "total": "65.9 ", "index_score": "91.9 "}
{"ranking": "7", "school": "南京大学", "local": "江苏", "total": "65.3 ", "index_score": "87.1 "}
{"ranking": "8", "school": "华中科技大学", "local": "湖北", "total": "63.0 ", "index_score": "80.6 "}
{"ranking": "9", "school": "中山大学", "local": "广东", "total": "62.7 ", "index_score": "81.1 "}
{"ranking": "10", "school": "哈尔滨工业大学", "local": "黑龙江", "total": "61.6 ", "index_score": "76.4 "}
{"ranking": "11", "school": "同济大学", "local": "上海", "total": "60.8 ", "index_score": "86.2 "}
{"ranking": "12", "school": "东南大学", "local": "江苏", "total": "59.8 ", "index_score": "80.5 "}
{"ranking": "13", "school": "武汉大学", "local": "湖北", "total": "58.4 ", "index_score": "82.5 "}
{"ranking": "14", "school": "北京航空航天大学", "local": "北京", "total": "58.3 ", "index_score": "85.5 "}
{"ranking": "15", "school": "南开大学", "local": "天津", "total": "58.2 ", "index_score": "86.5 "}
{"ranking": "16", "school": "四川大学", "local": "四川", "total": "57.4 ", "index_score": "74.5 "}
{"ranking": "16", "school": "西安交通大学", "local": "陕西", "total": "57.4 ", "index_score": "82.2 "}
{"ranking": "18", "school": "天津大学", "local": "天津", "total": "56.2 ", "index_score": "82.7 "}
{"ranking": "19", "school": "华南理工大学", "local": "广东", "total": "56.1 ", "index_score": "75.6 "}
{"ranking": "20", "school": "北京师范大学", "local": "北京", "total": "55.1 ", "index_score": "82.5 "}
{"ranking": "21", "school": "厦门大学", "local": "福建", "total": "55.0 ", "index_score": "81.5 "}
{"ranking": "22", "school": "山东大学", "local": "山东", "total": "54.5 ", "index_score": "71.9 "}
{"ranking": "23", "school": "大连理工大学", "local": "辽宁", "total": "54.1 ", "index_score": "74.0 "}
{"ranking": "24", "school": "吉林大学", "local": "吉林", "total": "53.9 ", "index_score": "72.3 "}
{"ranking": "25", "school": "北京理工大学", "local": "北京", "total": "53.1 ", "index_score": "80.4 "}
{"ranking": "26", "school": "中南大学", "local": "湖南", "total": "52.4 ", "index_score": "74.2 "}
{"ranking": "27", "school": "对外经济贸易大学", "local": "北京", "total": "51.9 ", "index_score": "84.5 "}
{"ranking": "28", "school": "苏州大学", "local": "江苏", "total": "51.7 ", "index_score": "65.1 "}
{"ranking": "28", "school": "中国人民大学", "local": "北京", "total": "51.7 ", "index_score": "90.0 "}
{"ranking": "30", "school": "西北工业大学", "local": "陕西", "total": "51.1 ", "index_score": "75.5 "}
{"ranking": "31", "school": "湖南大学", "local": "湖南", "total": "50.7 ", "index_score": "73.3 "}
{"ranking": "32", "school": "华东理工大学", "local": "上海", "total": "50.0 ", "index_score": "70.7 "}
{"ranking": "32", "school": "华东师范大学", "local": "上海", "total": "50.0 ", "index_score": "76.1 "}
{"ranking": "34", "school": "电子科技大学", "local": "四川", "total": "49.4 ", "index_score": "73.3 "}
{"ranking": "35", "school": "重庆大学", "local": "重庆", "total": "49.3 ", "index_score": "72.0 "}
{"ranking": "36", "school": "南京航空航天大学", "local": "江苏", "total": "49.1 ", "index_score": "70.8 "}
{"ranking": "37", "school": "北京科技大学", "local": "北京", "total": "48.9 ", "index_score": "73.2 "}
{"ranking": "38", "school": "上海财经大学", "local": "上海", "total": "48.8 ", "index_score": "84.5 "}
{"ranking": "39", "school": "南京理工大学", "local": "江苏", "total": "48.0 ", "index_score": "70.7 "}
{"ranking": "39", "school": "中国农业大学", "local": "北京", "total": "48.0 ", "index_score": "69.7 "}
{"ranking": "41", "school": "北京交通大学", "local": "北京", "total": "47.4 ", "index_score": "73.4 "}
{"ranking": "42", "school": "北京化工大学", "local": "北京", "total": "47.1 ", "index_score": "65.8 "}
{"ranking": "42", "school": "首都医科大学", "local": "北京", "total": "47.1 ", "index_score": "71.0 "}
{"ranking": "44", "school": "福州大学", "local": "福建", "total": "46.7 ", "index_score": "65.9 "}
{"ranking": "44", "school": "武汉理工大学", "local": "湖北", "total": "46.7 ", "index_score": "67.5 "}
{"ranking": "44", "school": "中央财经大学", "local": "北京", "total": "46.7 ", "index_score": "84.4 "}
{"ranking": "47", "school": "北京邮电大学", "local": "北京", "total": "46.6 ", "index_score": "77.4 "}
{"ranking": "47", "school": "东华大学", "local": "上海", "total": "46.6 ", "index_score": "65.6 "}
{"ranking": "47", "school": "华中师范大学", "local": "湖北", "total": "46.6 ", "index_score": "67.6 "}
{"ranking": "50", "school": "上海大学", "local": "上海", "total": "46.5 ", "index_score": "63.5 "}
{"ranking": "51", "school": "西安电子科技大学", "local": "陕西", "total": "46.2 ", "index_score": "70.3 "}
{"ranking": "52", "school": "北京协和医学院", "local": "北京", "total": "45.9 ", "index_score": "72.4 "}
{"ranking": "53", "school": "天津医科大学", "local": "天津", "total": "45.7 ", "index_score": "71.4 "}
{"ranking": "54", "school": "华北电力大学", "local": "北京", "total": "45.5 ", "index_score": "72.1 "}
{"ranking": "55", "school": "东北大学", "local": "辽宁", "total": "45.3 ", "index_score": "67.2 "}
{"ranking": "55", "school": "东北师范大学", "local": "吉林", "total": "45.3 ", "index_score": "63.7 "}
{"ranking": "57", "school": "暨南大学", "local": "广东", "total": "45.2 ", "index_score": "70.9 "}
{"ranking": "58", "school": "兰州大学", "local": "甘肃", "total": "45.0 ", "index_score": "66.3 "}
{"ranking": "59", "school": "江南大学", "local": "江苏", "total": "44.8 ", "index_score": "65.4 "}
{"ranking": "59", "school": "南京医科大学", "local": "江苏", "total": "44.8 ", "index_score": "60.7 "}
{"ranking": "61", "school": "中国海洋大学", "local": "山东", "total": "44.7 ", "index_score": "69.0 "}
{"ranking": "62", "school": "上海外国语大学", "local": "上海", "total": "44.5 ", "index_score": "75.8 "}
{"ranking": "63", "school": "中国地质大学（北京）", "local": "北京", "total": "44.3 ", "index_score": "63.9 "}
{"ranking": "64", "school": "西南财经大学", "local": "四川", "total": "44.1 ", "index_score": "76.7 "}
{"ranking": "65", "school": "中国地质大学（武汉）", "local": "湖北", "total": "44.0 ", "index_score": "63.5 "}
{"ranking": "66", "school": "华中农业大学", "local": "湖北", "total": "43.9 ", "index_score": "61.4 "}
{"ranking": "66", "school": "南方医科大学", "local": "广东", "total": "43.9 ", "index_score": "64.9 "}
{"ranking": "68", "school": "合肥工业大学", "local": "安徽", "total": "43.6 ", "index_score": "62.7 "}
{"ranking": "69", "school": "中国医科大学", "local": "辽宁", "total": "43.5 ", "index_score": "69.5 "}
{"ranking": "70", "school": "西南大学", "local": "重庆", "total": "43.4 ", "index_score": "59.9 "}
{"ranking": "71", "school": "南京农业大学", "local": "江苏", "total": "43.3 ", "index_score": "60.4 "}
{"ranking": "71", "school": "中国药科大学", "local": "江苏", "total": "43.3 ", "index_score": "66.3 "}
{"ranking": "71", "school": "中南财经政法大学", "local": "湖北", "total": "43.3 ", "index_score": "74.9 "}
{"ranking": "74", "school": "哈尔滨工程大学", "local": "黑龙江", "total": "43.2 ", "index_score": "67.5 "}
{"ranking": "74", "school": "中国石油大学（北京）", "local": "北京", "total": "43.2 ", "index_score": "66.0 "}
{"ranking": "76", "school": "浙江工业大学", "local": "浙江", "total": "43.0 ", "index_score": "64.7 "}
{"ranking": "77", "school": "东北财经大学", "local": "辽宁", "total": "42.9 ", "index_score": "70.3 "}
{"ranking": "77", "school": "河海大学", "local": "江苏", "total": "42.9 ", "index_score": "66.3 "}
{"ranking": "77", "school": "中国矿业大学", "local": "江苏", "total": "42.9 ", "index_score": "60.6 "}
{"ranking": "80", "school": "北京工业大学", "local": "北京", "total": "42.8 ", "index_score": "64.3 "}
{"ranking": "80", "school": "中国石油大学（华东）", "local": "山东", "total": "42.8 ", "index_score": "63.6 "}
{"ranking": "82", "school": "广东外语外贸大学", "local": "广东", "total": "42.7 ", "index_score": "64.3 "}
{"ranking": "83", "school": "南京师范大学", "local": "江苏", "total": "42.4 ", "index_score": "59.2 "}
{"ranking": "84", "school": "中国政法大学", "local": "北京", "total": "42.3 ", "index_score": "80.3 "}
{"ranking": "85", "school": "北京中医药大学", "local": "北京", "total": "42.0 ", "index_score": "68.6 "}
{"ranking": "85", "school": "西南交通大学", "local": "四川", "total": "42.0 ", "index_score": "61.3 "}
{"ranking": "87", "school": "华南师范大学", "local": "广东", "total": "41.9 ", "index_score": "61.8 "}
{"ranking": "87", "school": "中国传媒大学", "local": "北京", "total": "41.9 ", "index_score": "74.4 "}
{"ranking": "89", "school": "北京林业大学", "local": "北京", "total": "41.7 ", "index_score": "66.3 "}
{"ranking": "89", "school": "江苏大学", "local": "江苏", "total": "41.7 ", "index_score": "53.3 "}
{"ranking": "89", "school": "深圳大学", "local": "广东", "total": "41.7 ", "index_score": "57.9 "}
{"ranking": "92", "school": "汕头大学", "local": "广东", "total": "41.6 ", "index_score": "61.1 "}
{"ranking": "92", "school": "首都经济贸易大学", "local": "北京", "total": "41.6 ", "index_score": "63.3 "}
{"ranking": "92", "school": "西北农林科技大学", "local": "陕西", "total": "41.6 ", "index_score": "60.1 "}
{"ranking": "95", "school": "浙江师范大学", "local": "浙江", "total": "41.5 ", "index_score": "57.8 "}
{"ranking": "96", "school": "安徽大学", "local": "安徽", "total": "41.3 ", "index_score": "62.5 "}
{"ranking": "97", "school": "大连医科大学", "local": "辽宁", "total": "41.2 ", "index_score": "61.7 "}
{"ranking": "97", "school": "浙江理工大学", "local": "浙江", "total": "41.2 ", "index_score": "59.2 "}
{"ranking": "99", "school": "南京邮电大学", "local": "江苏", "total": "41.1 ", "index_score": "58.1 "}
{"ranking": "100", "school": "华侨大学", "local": "福建", "total": "41.0 ", "index_score": "58.0 "}
{"ranking": "100", "school": "宁波大学", "local": "浙江", "total": "41.0 ", "index_score": "58.9 "}
{"ranking": "102", "school": "西北大学", "local": "陕西", "total": "40.8 ", "index_score": "63.7 "}
{"ranking": "103", "school": "南京工业大学", "local": "江苏", "total": "40.7 ", "index_score": "53.9 "}
{"ranking": "103", "school": "上海中医药大学", "local": "上海", "total": "40.7 ", "index_score": "53.7 "}
{"ranking": "105", "school": "陕西师范大学", "local": "陕西", "total": "40.3 ", "index_score": "61.8 "}
{"ranking": "105", "school": "首都师范大学", "local": "北京", "total": "40.3 ", "index_score": "57.3 "}
{"ranking": "105", "school": "西交利物浦大学", "local": "江苏", "total": "40.3 ", "index_score": "56.5 "}
{"ranking": "108", "school": "杭州电子科技大学", "local": "浙江", "total": "40.1 ", "index_score": "58.7 "}
{"ranking": "109", "school": "杭州师范大学", "local": "浙江", "total": "40.0 ", "index_score": "53.0 "}
{"ranking": "109", "school": "燕山大学", "local": "河北", "total": "40.0 ", "index_score": "64.0 "}
{"ranking": "111", "school": "大连海事大学", "local": "辽宁", "total": "39.8 ", "index_score": "61.3 "}
{"ranking": "111", "school": "河北工业大学", "local": "河北", "total": "39.8 ", "index_score": "67.4 "}
{"ranking": "111", "school": "南京信息工程大学", "local": "江苏", "total": "39.8 ", "index_score": "52.8 "}
{"ranking": "114", "school": "中央民族大学", "local": "北京", "total": "39.7 ", "index_score": "63.2 "}
{"ranking": "115", "school": "沈阳药科大学", "local": "辽宁", "total": "39.6 ", "index_score": "57.4 "}
{"ranking": "116", "school": "天津财经大学", "local": "天津", "total": "39.5 ", "index_score": "67.9 "}
{"ranking": "117", "school": "哈尔滨医科大学", "local": "黑龙江", "total": "39.3 ", "index_score": "56.5 "}
{"ranking": "118", "school": "浙江工商大学", "local": "浙江", "total": "39.1 ", "index_score": "60.5 "}
{"ranking": "119", "school": "长安大学", "local": "陕西", "total": "39.0 ", "index_score": "63.9 "}
{"ranking": "119", "school": "湘潭大学", "local": "湖南", "total": "39.0 ", "index_score": "55.5 "}
{"ranking": "121", "school": "云南大学", "local": "云南", "total": "38.9 ", "index_score": "56.6 "}
{"ranking": "122", "school": "重庆医科大学", "local": "重庆", "total": "38.7 ", "index_score": "54.7 "}
{"ranking": "122", "school": "南京财经大学", "local": "江苏", "total": "38.7 ", "index_score": "56.7 "}
{"ranking": "122", "school": "上海理工大学", "local": "上海", "total": "38.7 ", "index_score": "57.8 "}
{"ranking": "125", "school": "湖北大学", "local": "湖北", "total": "38.6 ", "index_score": "57.3 "}
{"ranking": "125", "school": "湖南师范大学", "local": "湖南", "total": "38.6 ", "index_score": "61.3 "}
{"ranking": "127", "school": "扬州大学", "local": "江苏", "total": "38.5 ", "index_score": "49.2 "}
{"ranking": "128", "school": "温州医科大学", "local": "浙江", "total": "38.3 ", "index_score": "51.8 "}
{"ranking": "128", "school": "浙江财经大学", "local": "浙江", "total": "38.3 ", "index_score": "57.9 "}
{"ranking": "130", "school": "安徽医科大学", "local": "安徽", "total": "38.2 ", "index_score": "55.7 "}
{"ranking": "130", "school": "福建医科大学", "local": "福建", "total": "38.2 ", "index_score": "58.6 "}
{"ranking": "132", "school": "广东工业大学", "local": "广东", "total": "38.1 ", "index_score": "53.9 "}
{"ranking": "133", "school": "广州医科大学", "local": "广东", "total": "37.9 ", "index_score": "55.0 "}
{"ranking": "133", "school": "河北医科大学", "local": "河北", "total": "37.9 ", "index_score": "58.5 "}
{"ranking": "133", "school": "辽宁大学", "local": "辽宁", "total": "37.9 ", "index_score": "58.2 "}
{"ranking": "133", "school": "上海师范大学", "local": "上海", "total": "37.9 ", "index_score": "48.2 "}
{"ranking": "137", "school": "河北大学", "local": "河北", "total": "37.7 ", "index_score": "60.0 "}
{"ranking": "137", "school": "华南农业大学", "local": "广东", "total": "37.7 ", "index_score": "52.4 "}
{"ranking": "139", "school": "南昌大学", "local": "江西", "total": "37.6 ", "index_score": "51.8 "}
{"ranking": "139", "school": "太原理工大学", "local": "山西", "total": "37.6 ", "index_score": "58.5 "}
{"ranking": "141", "school": "南京审计大学", "local": "江苏", "total": "37.5 ", "index_score": "58.4 "}
{"ranking": "142", "school": "广西大学", "local": "广西", "total": "37.4 ", "index_score": "56.8 "}
{"ranking": "143", "school": "山西大学", "local": "山西", "total": "37.3 ", "index_score": "53.7 "}
{"ranking": "143", "school": "郑州大学", "local": "河南", "total": "37.3 ", "index_score": "44.9 "}
{"ranking": "145", "school": "广西医科大学", "local": "广西", "total": "37.1 ", "index_score": "52.6 "}
{"ranking": "146", "school": "东北林业大学", "local": "黑龙江", "total": "37.0 ", "index_score": "57.7 "}
{"ranking": "147", "school": "东北农业大学", "local": "黑龙江", "total": "36.9 ", "index_score": "54.8 "}
{"ranking": "148", "school": "武汉科技大学", "local": "湖北", "total": "36.8 ", "index_score": "57.8 "}
{"ranking": "149", "school": "石家庄铁道大学", "local": "河北", "total": "36.7 ", "index_score": "59.0 "}
{"ranking": "150", "school": "渤海大学", "local": "辽宁", "total": "36.6 ", "index_score": "37.4 "}
{"ranking": "151", "school": "安徽师范大学", "local": "安徽", "total": "36.4 ", "index_score": "47.3 "}
{"ranking": "152", "school": "长沙理工大学", "local": "湖南", "total": "36.3 ", "index_score": "53.9 "}
{"ranking": "152", "school": "福建师范大学", "local": "福建", "total": "36.3 ", "index_score": "50.0 "}
{"ranking": "152", "school": "黑龙江大学", "local": "黑龙江", "total": "36.3 ", "index_score": "46.8 "}
{"ranking": "152", "school": "江西财经大学", "local": "江西", "total": "36.3 ", "index_score": "55.3 "}
{"ranking": "156", "school": "广州大学", "local": "广东", "total": "36.2 ", "index_score": "52.5 "}
{"ranking": "157", "school": "北京工商大学", "local": "北京", "total": "36.1 ", "index_score": "54.4 "}
{"ranking": "157", "school": "河北师范大学", "local": "河北", "total": "36.1 ", "index_score": "54.4 "}
{"ranking": "157", "school": "三峡大学", "local": "湖北", "total": "36.1 ", "index_score": "50.9 "}
{"ranking": "157", "school": "天津师范大学", "local": "天津", "total": "36.1 ", "index_score": "51.4 "}
{"ranking": "157", "school": "温州大学", "local": "浙江", "total": "36.1 ", "index_score": "45.9 "}
{"ranking": "162", "school": "安徽工业大学", "local": "安徽", "total": "35.9 ", "index_score": "46.9 "}
{"ranking": "162", "school": "河北科技大学", "local": "河北", "total": "35.9 ", "index_score": "53.5 "}
{"ranking": "164", "school": "青岛大学", "local": "山东", "total": "35.8 ", "index_score": "45.9 "}
{"ranking": "165", "school": "辽宁工业大学", "local": "辽宁", "total": "35.7 ", "index_score": "34.3 "}
{"ranking": "165", "school": "上海海事大学", "local": "上海", "total": "35.7 ", "index_score": "48.3 "}
{"ranking": "167", "school": "徐州医科大学", "local": "江苏", "total": "35.6 ", "index_score": "49.8 "}
{"ranking": "168", "school": "天津工业大学", "local": "天津", "total": "35.5 ", "index_score": "47.8 "}
{"ranking": "169", "school": "北京体育大学", "local": "北京", "total": "35.4 ", "index_score": "57.6 "}
{"ranking": "169", "school": "四川农业大学", "local": "四川", "total": "35.4 ", "index_score": "49.1 "}
{"ranking": "171", "school": "西安理工大学", "local": "陕西", "total": "35.3 ", "index_score": "54.1 "}
{"ranking": "172", "school": "河南大学", "local": "河南", "total": "35.2 ", "index_score": "47.0 "}
{"ranking": "172", "school": "武汉工程大学", "local": "湖北", "total": "35.2 ", "index_score": "50.2 "}
{"ranking": "174", "school": "广州中医药大学", "local": "广东", "total": "35.1 ", "index_score": "52.1 "}
{"ranking": "174", "school": "天津中医药大学", "local": "天津", "total": "35.1 ", "index_score": "45.8 "}
{"ranking": "176", "school": "重庆邮电大学", "local": "重庆", "total": "35.0 ", "index_score": "50.9 "}
{"ranking": "176", "school": "济南大学", "local": "山东", "total": "35.0 ", "index_score": "40.2 "}
{"ranking": "176", "school": "闽南师范大学", "local": "福建", "total": "35.0 ", "index_score": "41.0 "}
{"ranking": "179", "school": "北京建筑大学", "local": "北京", "total": "34.9 ", "index_score": "51.4 "}
{"ranking": "180", "school": "重庆工商大学", "local": "重庆", "total": "34.8 ", "index_score": "45.7 "}
{"ranking": "180", "school": "福建农林大学", "local": "福建", "total": "34.8 ", "index_score": "44.7 "}
{"ranking": "180", "school": "青岛科技大学", "local": "山东", "total": "34.8 ", "index_score": "43.9 "}
{"ranking": "180", "school": "沈阳航空航天大学", "local": "辽宁", "total": "34.8 ", "index_score": "46.3 "}
{"ranking": "184", "school": "河北农业大学", "local": "河北", "total": "34.7 ", "index_score": "50.7 "}
{"ranking": "184", "school": "江苏师范大学", "local": "江苏", "total": "34.7 ", "index_score": "40.1 "}
{"ranking": "184", "school": "浙江农林大学", "local": "浙江", "total": "34.7 ", "index_score": "44.6 "}
{"ranking": "187", "school": "北方工业大学", "local": "北京", "total": "34.6 ", "index_score": "48.9 "}
{"ranking": "187", "school": "天津理工大学", "local": "天津", "total": "34.6 ", "index_score": "45.2 "}
{"ranking": "187", "school": "西安建筑科技大学", "local": "陕西", "total": "34.6 ", "index_score": "53.6 "}
{"ranking": "190", "school": "中国计量大学", "local": "浙江", "total": "34.5 ", "index_score": "46.2 "}
{"ranking": "191", "school": "长春理工大学", "local": "吉林", "total": "34.4 ", "index_score": "52.1 "}
{"ranking": "191", "school": "中国民航大学", "local": "天津", "total": "34.4 ", "index_score": "53.9 "}
{"ranking": "191", "school": "中南民族大学", "local": "湖北", "total": "34.4 ", "index_score": "43.4 "}
{"ranking": "194", "school": "福建中医药大学", "local": "福建", "total": "34.3 ", "index_score": "46.1 "}
{"ranking": "194", "school": "海南大学", "local": "海南", "total": "34.3 ", "index_score": "51.0 "}
{"ranking": "194", "school": "集美大学", "local": "福建", "total": "34.3 ", "index_score": "49.6 "}
{"ranking": "194", "school": "南通大学", "local": "江苏", "total": "34.3 ", "index_score": "41.5 "}
{"ranking": "198", "school": "黑龙江中医药大学", "local": "黑龙江", "total": "34.2 ", "index_score": "40.5 "}
{"ranking": "198", "school": "湖南农业大学", "local": "湖南", "total": "34.2 ", "index_score": "43.3 "}
{"ranking": "200", "school": "辽宁师范大学", "local": "辽宁", "total": "34.1 ", "index_score": "48.9 "}
{"ranking": "200", "school": "上海海洋大学", "local": "上海", "total": "34.1 ", "index_score": "40.7 "}
{"ranking": "202", "school": "南京中医药大学", "local": "江苏", "total": "34.0 ", "index_score": "45.1 "}
{"ranking": "202", "school": "宁夏医科大学", "local": "宁夏", "total": "34.0 ", "index_score": "45.7 "}
{"ranking": "202", "school": "浙江中医药大学", "local": "浙江", "total": "34.0 ", "index_score": "44.4 "}
{"ranking": "205", "school": "广西师范大学", "local": "广西", "total": "33.9 ", "index_score": "43.2 "}
{"ranking": "205", "school": "云南师范大学", "local": "云南", "total": "33.9 ", "index_score": "38.3 "}
{"ranking": "207", "school": "山东师范大学", "local": "山东", "total": "33.8 ", "index_score": "47.0 "}
{"ranking": "208", "school": "北京物资学院", "local": "北京", "total": "33.7 ", "index_score": "41.1 "}
{"ranking": "208", "school": "沈阳医学院", "local": "辽宁", "total": "33.7 ", "index_score": "40.9 "}
{"ranking": "210", "school": "河南师范大学", "local": "河南", "total": "33.6 ", "index_score": "42.3 "}
{"ranking": "210", "school": "西南石油大学", "local": "四川", "total": "33.6 ", "index_score": "46.3 "}
{"ranking": "212", "school": "常州大学", "local": "江苏", "total": "33.5 ", "index_score": "43.0 "}
{"ranking": "212", "school": "山西财经大学", "local": "山西", "total": "33.5 ", "index_score": "51.9 "}
{"ranking": "214", "school": "承德医学院", "local": "河北", "total": "33.4 ", "index_score": "51.7 "}
{"ranking": "214", "school": "江西师范大学", "local": "江西", "total": "33.4 ", "index_score": "38.9 "}
{"ranking": "214", "school": "新乡医学院", "local": "河南", "total": "33.4 ", "index_score": "48.2 "}
{"ranking": "214", "school": "延边大学", "local": "吉林", "total": "33.4 ", "index_score": "48.8 "}
{"ranking": "218", "school": "重庆交通大学", "local": "重庆", "total": "33.3 ", "index_score": "48.5 "}
{"ranking": "218", "school": "昆明医科大学", "local": "云南", "total": "33.3 ", "index_score": "44.9 "}
{"ranking": "220", "school": "湖州师范学院", "local": "浙江", "total": "33.2 ", "index_score": "38.9 "}
{"ranking": "220", "school": "山西师范大学", "local": "山西", "total": "33.2 ", "index_score": "47.5 "}
{"ranking": "220", "school": "天津科技大学", "local": "天津", "total": "33.2 ", "index_score": "44.9 "}
{"ranking": "223", "school": "河北经贸大学", "local": "河北", "total": "33.1 ", "index_score": "54.7 "}
{"ranking": "223", "school": "内蒙古大学", "local": "内蒙古", "total": "33.1 ", "index_score": "46.4 "}
{"ranking": "223", "school": "信阳师范学院", "local": "河南", "total": "33.1 ", "index_score": "36.1 "}
{"ranking": "226", "school": "长江大学", "local": "湖北", "total": "33.0 ", "index_score": "45.3 "}
{"ranking": "226", "school": "河南理工大学", "local": "河南", "total": "33.0 ", "index_score": "44.2 "}
{"ranking": "226", "school": "南华大学", "local": "湖南", "total": "33.0 ", "index_score": "46.1 "}
{"ranking": "226", "school": "武汉轻工大学", "local": "湖北", "total": "33.0 ", "index_score": "42.8 "}
{"ranking": "230", "school": "广东医科大学", "local": "广东", "total": "32.9 ", "index_score": "39.3 "}
{"ranking": "230", "school": "河北北方学院", "local": "河北", "total": "32.9 ", "index_score": "45.2 "}
{"ranking": "230", "school": "上海立信会计学院", "local": "上海", "total": "32.9 ", "index_score": "49.3 "}
{"ranking": "233", "school": "广东药科大学", "local": "广东", "total": "32.8 ", "index_score": "39.9 "}
{"ranking": "233", "school": "山东科技大学", "local": "山东", "total": "32.8 ", "index_score": "42.8 "}
{"ranking": "233", "school": "苏州科技大学", "local": "江苏", "total": "32.8 ", "index_score": "40.1 "}
{"ranking": "236", "school": "北京信息科技大学", "local": "北京", "total": "32.7 ", "index_score": "46.4 "}
{"ranking": "236", "school": "黄冈师范学院", "local": "湖北", "total": "32.7 ", "index_score": "34.1 "}
{"ranking": "238", "school": "湖南科技大学", "local": "湖南", "total": "32.6 ", "index_score": "46.8 "}
{"ranking": "238", "school": "陕西科技大学", "local": "陕西", "total": "32.6 ", "index_score": "48.1 "}
{"ranking": "240", "school": "重庆师范大学", "local": "重庆", "total": "32.5 ", "index_score": "40.9 "}
{"ranking": "240", "school": "湖南工业大学", "local": "湖南", "total": "32.5 ", "index_score": "38.4 "}
{"ranking": "240", "school": "江汉大学", "local": "湖北", "total": "32.5 ", "index_score": "45.2 "}
{"ranking": "240", "school": "江苏科技大学", "local": "江苏", "total": "32.5 ", "index_score": "46.5 "}
{"ranking": "240", "school": "中南林业科技大学", "local": "湖南", "total": "32.5 ", "index_score": "46.6 "}
{"ranking": "245", "school": "东北电力大学", "local": "吉林", "total": "32.4 ", "index_score": "49.3 "}
{"ranking": "245", "school": "山东财经大学", "local": "山东", "total": "32.4 ", "index_score": "49.9 "}
{"ranking": "247", "school": "华北理工大学", "local": "河北", "total": "32.3 ", "index_score": "47.2 "}
{"ranking": "247", "school": "山东农业大学", "local": "山东", "total": "32.3 ", "index_score": "35.0 "}
{"ranking": "247", "school": "西南医科大学", "local": "四川", "total": "32.3 ", "index_score": "44.5 "}
{"ranking": "247", "school": "中北大学", "local": "山西", "total": "32.3 ", "index_score": "49.8 "}
{"ranking": "251", "school": "成都理工大学", "local": "四川", "total": "32.2 ", "index_score": "44.2 "}
{"ranking": "251", "school": "广东财经大学", "local": "广东", "total": "32.2 ", "index_score": "47.1 "}
{"ranking": "251", "school": "西安邮电大学", "local": "陕西", "total": "32.2 ", "index_score": "48.5 "}
{"ranking": "251", "school": "浙江科技学院", "local": "浙江", "total": "32.2 ", "index_score": "40.7 "}
{"ranking": "255", "school": "安徽农业大学", "local": "安徽", "total": "32.0 ", "index_score": "40.5 "}
{"ranking": "255", "school": "昆明理工大学", "local": "云南", "total": "32.0 ", "index_score": "39.1 "}
{"ranking": "255", "school": "宁夏大学", "local": "宁夏", "total": "32.0 ", "index_score": "43.5 "}
{"ranking": "258", "school": "锦州医科大学", "local": "辽宁", "total": "31.8 ", "index_score": "39.7 "}
{"ranking": "258", "school": "烟台大学", "local": "山东", "total": "31.8 ", "index_score": "35.3 "}
{"ranking": "260", "school": "贵州大学", "local": "贵州", "total": "31.7 ", "index_score": "42.8 "}
{"ranking": "260", "school": "吉林师范大学", "local": "吉林", "total": "31.7 ", "index_score": "45.3 "}
{"ranking": "260", "school": "山西医科大学", "local": "山西", "total": "31.7 ", "index_score": "48.8 "}
{"ranking": "260", "school": "绍兴文理学院", "local": "浙江", "total": "31.7 ", "index_score": "38.6 "}
{"ranking": "260", "school": "沈阳农业大学", "local": "辽宁", "total": "31.7 ", "index_score": "46.4 "}
{"ranking": "265", "school": "广西民族大学", "local": "广西", "total": "31.6 ", "index_score": "36.5 "}
{"ranking": "265", "school": "兰州交通大学", "local": "甘肃", "total": "31.6 ", "index_score": "43.0 "}
{"ranking": "265", "school": "闽江学院", "local": "福建", "total": "31.6 ", "index_score": "34.8 "}
{"ranking": "265", "school": "沈阳建筑大学", "local": "辽宁", "total": "31.6 ", "index_score": "49.2 "}
{"ranking": "265", "school": "西北师范大学", "local": "甘肃", "total": "31.6 ", "index_score": "40.2 "}
{"ranking": "270", "school": "大连交通大学", "local": "辽宁", "total": "31.5 ", "index_score": "47.6 "}
{"ranking": "270", "school": "湖北师范大学", "local": "湖北", "total": "31.5 ", "index_score": "38.3 "}
{"ranking": "270", "school": "南京林业大学", "local": "江苏", "total": "31.5 ", "index_score": "36.3 "}
{"ranking": "270", "school": "青岛理工大学", "local": "山东", "total": "31.5 ", "index_score": "42.6 "}
{"ranking": "270", "school": "上海电力学院", "local": "上海", "total": "31.5 ", "index_score": "37.0 "}
{"ranking": "275", "school": "广东技术师范学院", "local": "广东", "total": "31.4 ", "index_score": "39.0 "}
{"ranking": "275", "school": "河南科技大学", "local": "河南", "total": "31.4 ", "index_score": "40.4 "}
{"ranking": "275", "school": "淮北师范大学", "local": "安徽", "total": "31.4 ", "index_score": "33.1 "}
{"ranking": "275", "school": "辽宁中医药大学", "local": "辽宁", "total": "31.4 ", "index_score": "40.4 "}
{"ranking": "275", "school": "上海第二工业大学", "local": "上海", "total": "31.4 ", "index_score": "35.0 "}
{"ranking": "275", "school": "沈阳师范大学", "local": "辽宁", "total": "31.4 ", "index_score": "39.1 "}
{"ranking": "281", "school": "哈尔滨师范大学", "local": "黑龙江", "total": "31.3 ", "index_score": "42.9 "}
{"ranking": "281", "school": "沈阳工业大学", "local": "辽宁", "total": "31.3 ", "index_score": "45.4 "}
{"ranking": "281", "school": "厦门理工学院", "local": "福建", "total": "31.3 ", "index_score": "41.3 "}
{"ranking": "284", "school": "常熟理工学院", "local": "江苏", "total": "31.2 ", "index_score": "34.8 "}
{"ranking": "284", "school": "哈尔滨理工大学", "local": "黑龙江", "total": "31.2 ", "index_score": "44.2 "}
{"ranking": "284", "school": "河南工业大学", "local": "河南", "total": "31.2 ", "index_score": "40.9 "}
{"ranking": "287", "school": "桂林电子科技大学", "local": "广西", "total": "31.1 ", "index_score": "39.8 "}
{"ranking": "287", "school": "兰州理工大学", "local": "甘肃", "total": "31.1 ", "index_score": "38.5 "}
{"ranking": "287", "school": "浙江海洋大学", "local": "浙江", "total": "31.1 ", "index_score": "38.2 "}
{"ranking": "290", "school": "大连大学", "local": "辽宁", "total": "31.0 ", "index_score": "41.1 "}
{"ranking": "290", "school": "河北地质大学", "local": "河北", "total": "31.0 ", "index_score": "42.4 "}
{"ranking": "290", "school": "西华师范大学", "local": "四川", "total": "31.0 ", "index_score": "29.5 "}
{"ranking": "293", "school": "大连海洋大学", "local": "辽宁", "total": "30.9 ", "index_score": "37.9 "}
{"ranking": "293", "school": "大连民族大学", "local": "辽宁", "total": "30.9 ", "index_score": "38.2 "}
{"ranking": "293", "school": "曲阜师范大学", "local": "山东", "total": "30.9 ", "index_score": "32.1 "}
{"ranking": "293", "school": "唐山学院", "local": "河北", "total": "30.9 ", "index_score": "46.8 "}
{"ranking": "297", "school": "广东海洋大学", "local": "广东", "total": "30.8 ", "index_score": "35.1 "}
{"ranking": "297", "school": "河北工程大学", "local": "河北", "total": "30.8 ", "index_score": "44.7 "}
{"ranking": "297", "school": "河南农业大学", "local": "河南", "total": "30.8 ", "index_score": "37.8 "}
{"ranking": "297", "school": "嘉兴学院", "local": "浙江", "total": "30.8 ", "index_score": "35.7 "}
{"ranking": "297", "school": "石家庄学院", "local": "河北", "total": "30.8 ", "index_score": "45.4 "}
{"ranking": "302", "school": "海南医学院", "local": "海南", "total": "30.6 ", "index_score": "35.6 "}
{"ranking": "302", "school": "河南中医药大学", "local": "河南", "total": "30.6 ", "index_score": "42.4 "}
{"ranking": "302", "school": "淮阴师范学院", "local": "江苏", "total": "30.6 ", "index_score": "29.7 "}
{"ranking": "302", "school": "上海应用技术大学", "local": "上海", "total": "30.6 ", "index_score": "31.3 "}
{"ranking": "302", "school": "郑州航空工业管理学院", "local": "河南", "total": "30.6 ", "index_score": "39.7 "}
{"ranking": "307", "school": "大连工业大学", "local": "辽宁", "total": "30.5 ", "index_score": "39.2 "}
{"ranking": "307", "school": "辽宁工程技术大学", "local": "辽宁", "total": "30.5 ", "index_score": "44.7 "}
{"ranking": "307", "school": "太原科技大学", "local": "山西", "total": "30.5 ", "index_score": "43.6 "}
{"ranking": "307", "school": "郑州师范学院", "local": "河南", "total": "30.5 ", "index_score": "32.5 "}
{"ranking": "311", "school": "大理大学", "local": "云南", "total": "30.4 ", "index_score": "29.7 "}
{"ranking": "311", "school": "桂林理工大学", "local": "广西", "total": "30.4 ", "index_score": "36.4 "}
{"ranking": "311", "school": "桂林医学院", "local": "广西", "total": "30.4 ", "index_score": "38.0 "}
{"ranking": "311", "school": "上海工程技术大学", "local": "上海", "total": "30.4 ", "index_score": "37.5 "}
{"ranking": "311", "school": "石河子大学", "local": "新疆", "total": "30.4 ", "index_score": "37.7 "}
{"ranking": "316", "school": "北京印刷学院", "local": "北京", "total": "30.3 ", "index_score": "38.8 "}
{"ranking": "316", "school": "长春工业大学", "local": "吉林", "total": "30.3 ", "index_score": "42.4 "}
{"ranking": "316", "school": "成都中医药大学", "local": "四川", "total": "30.3 ", "index_score": "37.3 "}
{"ranking": "316", "school": "海南师范大学", "local": "海南", "total": "30.3 ", "index_score": "33.0 "}
{"ranking": "320", "school": "长春大学", "local": "吉林", "total": "30.2 ", "index_score": "40.1 "}
{"ranking": "320", "school": "广西中医药大学", "local": "广西", "total": "30.2 ", "index_score": "40.1 "}
{"ranking": "320", "school": "四川师范大学", "local": "四川", "total": "30.2 ", "index_score": "35.8 "}
{"ranking": "320", "school": "唐山师范学院", "local": "河北", "total": "30.2 ", "index_score": "41.8 "}
{"ranking": "324", "school": "华东交通大学", "local": "江西", "total": "30.1 ", "index_score": "42.0 "}
{"ranking": "324", "school": "吉首大学", "local": "湖南", "total": "30.1 ", "index_score": "36.0 "}
{"ranking": "324", "school": "南昌航空大学", "local": "江西", "total": "30.1 ", "index_score": "36.3 "}
{"ranking": "324", "school": "西南民族大学", "local": "四川", "total": "30.1 ", "index_score": "34.1 "}
{"ranking": "328", "school": "安徽理工大学", "local": "安徽", "total": "30.0 ", "index_score": "39.0 "}
{"ranking": "328", "school": "安阳师范学院", "local": "河南", "total": "30.0 ", "index_score": "29.3 "}
{"ranking": "328", "school": "川北医学院", "local": "四川", "total": "30.0 ", "index_score": "37.0 "}
{"ranking": "328", "school": "东北石油大学", "local": "黑龙江", "total": "30.0 ", "index_score": "49.8 "}
{"ranking": "328", "school": "福建工程学院", "local": "福建", "total": "30.0 ", "index_score": "37.8 "}
{"ranking": "328", "school": "哈尔滨商业大学", "local": "黑龙江", "total": "30.0 ", "index_score": "44.6 "}
{"ranking": "328", "school": "天津商业大学", "local": "天津", "total": "30.0 ", "index_score": "42.3 "}
{"ranking": "335", "school": "长治医学院", "local": "山西", "total": "29.9 ", "index_score": "42.2 "}
{"ranking": "335", "school": "湖北工程学院", "local": "湖北", "total": "29.9 ", "index_score": "36.1 "}
{"ranking": "335", "school": "西安财经学院", "local": "陕西", "total": "29.9 ", "index_score": "43.2 "}
{"ranking": "335", "school": "西安石油大学", "local": "陕西", "total": "29.9 ", "index_score": "43.5 "}
{"ranking": "339", "school": "广西师范学院", "local": "广西", "total": "29.8 ", "index_score": "36.5 "}
{"ranking": "339", "school": "宁波工程学院", "local": "浙江", "total": "29.8 ", "index_score": "32.8 "}
{"ranking": "341", "school": "廊坊师范学院", "local": "河北", "total": "29.7 ", "index_score": "43.2 "}
{"ranking": "342", "school": "东莞理工学院", "local": "广东", "total": "29.6 ", "index_score": "35.7 "}
{"ranking": "342", "school": "湖南理工学院", "local": "湖南", "total": "29.6 ", "index_score": "32.4 "}
{"ranking": "342", "school": "西南科技大学", "local": "四川", "total": "29.6 ", "index_score": "39.5 "}
{"ranking": "345", "school": "蚌埠医学院", "local": "安徽", "total": "29.5 ", "index_score": "36.3 "}
{"ranking": "345", "school": "齐齐哈尔医学院", "local": "黑龙江", "total": "29.5 ", "index_score": "33.2 "}
{"ranking": "345", "school": "山西农业大学", "local": "山西", "total": "29.5 ", "index_score": "40.1 "}
{"ranking": "348", "school": "长春师范大学", "local": "吉林", "total": "29.4 ", "index_score": "39.5 "}
{"ranking": "348", "school": "五邑大学", "local": "广东", "total": "29.4 ", "index_score": "34.6 "}
{"ranking": "350", "school": "潍坊医学院", "local": "山东", "total": "29.2 ", "index_score": "33.3 "}
{"ranking": "351", "school": "成都信息工程大学", "local": "四川", "total": "29.1 ", "index_score": "37.5 "}
{"ranking": "351", "school": "湖北汽车工业学院", "local": "湖北", "total": "29.1 ", "index_score": "38.4 "}
{"ranking": "351", "school": "吉林农业大学", "local": "吉林", "total": "29.1 ", "index_score": "33.1 "}
{"ranking": "351", "school": "山东中医药大学", "local": "山东", "total": "29.1 ", "index_score": "33.2 "}
{"ranking": "351", "school": "沈阳理工大学", "local": "辽宁", "total": "29.1 ", "index_score": "42.7 "}
{"ranking": "356", "school": "吉林建筑大学", "local": "吉林", "total": "29.0 ", "index_score": "38.3 "}
{"ranking": "356", "school": "内蒙古医科大学", "local": "内蒙古", "total": "29.0 ", "index_score": "37.9 "}
{"ranking": "356", "school": "山东理工大学", "local": "山东", "total": "29.0 ", "index_score": "34.2 "}
{"ranking": "356", "school": "盐城工学院", "local": "江苏", "total": "29.0 ", "index_score": "31.9 "}
{"ranking": "360", "school": "滨州医学院", "local": "山东", "total": "28.9 ", "index_score": "32.0 "}
{"ranking": "360", "school": "济宁医学院", "local": "山东", "total": "28.9 ", "index_score": "25.5 "}
{"ranking": "360", "school": "山西大同大学", "local": "山西", "total": "28.9 ", "index_score": "39.1 "}
{"ranking": "360", "school": "沈阳大学", "local": "辽宁", "total": "28.9 ", "index_score": "35.7 "}
{"ranking": "360", "school": "西安工程大学", "local": "陕西", "total": "28.9 ", "index_score": "39.7 "}
{"ranking": "360", "school": "西华大学", "local": "四川", "total": "28.9 ", "index_score": "36.8 "}
{"ranking": "360", "school": "延安大学", "local": "陕西", "total": "28.9 ", "index_score": "39.4 "}
{"ranking": "367", "school": "辽宁科技大学", "local": "辽宁", "total": "28.8 ", "index_score": "35.4 "}
{"ranking": "367", "school": "辽宁石油化工大学", "local": "辽宁", "total": "28.8 ", "index_score": "36.9 "}
{"ranking": "367", "school": "陕西理工大学", "local": "陕西", "total": "28.8 ", "index_score": "35.2 "}
{"ranking": "367", "school": "沈阳工程学院", "local": "辽宁", "total": "28.8 ", "index_score": "36.7 "}
{"ranking": "367", "school": "玉林师范学院", "local": "广西", "total": "28.8 ", "index_score": "28.8 "}
{"ranking": "372", "school": "长沙学院", "local": "湖南", "total": "28.7 ", "index_score": "33.3 "}
{"ranking": "372", "school": "湖北理工学院", "local": "湖北", "total": "28.7 ", "index_score": "36.7 "}
{"ranking": "372", "school": "山东建筑大学", "local": "山东", "total": "28.7 ", "index_score": "35.6 "}
{"ranking": "372", "school": "泰山医学院", "local": "山东", "total": "28.7 ", "index_score": "27.3 "}
{"ranking": "372", "school": "天津城建大学", "local": "天津", "total": "28.7 ", "index_score": "38.1 "}
{"ranking": "372", "school": "皖南医学院", "local": "安徽", "total": "28.7 ", "index_score": "31.8 "}
{"ranking": "372", "school": "徐州工程学院", "local": "江苏", "total": "28.7 ", "index_score": "31.1 "}
{"ranking": "379", "school": "湖南商学院", "local": "湖南", "total": "28.6 ", "index_score": "41.7 "}
{"ranking": "380", "school": "北京联合大学", "local": "北京", "total": "28.5 ", "index_score": "29.9 "}
{"ranking": "380", "school": "北京石油化工学院", "local": "北京", "total": "28.5 ", "index_score": "33.6 "}
{"ranking": "380", "school": "东华理工大学", "local": "江西", "total": "28.5 ", "index_score": "29.1 "}
{"ranking": "380", "school": "江西科技师范大学", "local": "江西", "total": "28.5 ", "index_score": "28.3 "}
{"ranking": "380", "school": "青海大学", "local": "青海", "total": "28.5 ", "index_score": "37.3 "}
{"ranking": "385", "school": "河南科技学院", "local": "河南", "total": "28.4 ", "index_score": "32.9 "}
{"ranking": "386", "school": "聊城大学", "local": "山东", "total": "28.3 ", "index_score": "23.1 "}
{"ranking": "386", "school": "南阳师范学院", "local": "河南", "total": "28.3 ", "index_score": "28.4 "}
{"ranking": "388", "school": "贵州医科大学", "local": "贵州", "total": "28.2 ", "index_score": "31.4 "}
{"ranking": "388", "school": "金陵科技学院", "local": "江苏", "total": "28.2 ", "index_score": "37.6 "}
{"ranking": "388", "school": "龙岩学院", "local": "福建", "total": "28.2 ", "index_score": "24.6 "}
{"ranking": "388", "school": "鲁东大学", "local": "山东", "total": "28.2 ", "index_score": "29.9 "}
{"ranking": "388", "school": "盐城师范学院", "local": "江苏", "total": "28.2 ", "index_score": "29.5 "}
{"ranking": "388", "school": "中原工学院", "local": "河南", "total": "28.2 ", "index_score": "33.1 "}
{"ranking": "394", "school": "北京服装学院", "local": "北京", "total": "28.1 ", "index_score": "34.7 "}
{"ranking": "394", "school": "肇庆学院", "local": "广东", "total": "28.1 ", "index_score": "29.8 "}
{"ranking": "396", "school": "天津农学院", "local": "天津", "total": "28.0 ", "index_score": "31.1 "}
{"ranking": "397", "school": "江西农业大学", "local": "江西", "total": "27.9 ", "index_score": "30.1 "}
{"ranking": "397", "school": "太原工业学院", "local": "山西", "total": "27.9 ", "index_score": "39.6 "}
{"ranking": "397", "school": "云南农业大学", "local": "云南", "total": "27.9 ", "index_score": "27.4 "}
{"ranking": "400", "school": "湖南文理学院", "local": "湖南", "total": "27.8 ", "index_score": "28.3 "}
{"ranking": "400", "school": "华北水利水电大学", "local": "河南", "total": "27.8 ", "index_score": "40.1 "}
{"ranking": "400", "school": "江西理工大学", "local": "江西", "total": "27.8 ", "index_score": "31.9 "}
{"ranking": "400", "school": "洛阳师范学院", "local": "河南", "total": "27.8 ", "index_score": "30.7 "}
{"ranking": "400", "school": "莆田学院", "local": "福建", "total": "27.8 ", "index_score": "30.7 "}
{"ranking": "400", "school": "齐鲁工业大学", "local": "山东", "total": "27.8 ", "index_score": "24.3 "}
{"ranking": "400", "school": "青岛农业大学", "local": "山东", "total": "27.8 ", "index_score": "24.0 "}
{"ranking": "400", "school": "西南林业大学", "local": "云南", "total": "27.8 ", "index_score": "29.5 "}
{"ranking": "408", "school": "宝鸡文理学院", "local": "陕西", "total": "27.7 ", "index_score": "34.8 "}
{"ranking": "408", "school": "成都医学院", "local": "四川", "total": "27.7 ", "index_score": "30.7 "}
{"ranking": "408", "school": "淮海工学院", "local": "江苏", "total": "27.7 ", "index_score": "31.5 "}
{"ranking": "411", "school": "北华大学", "local": "吉林", "total": "27.6 ", "index_score": "37.3 "}
{"ranking": "411", "school": "重庆科技学院", "local": "重庆", "total": "27.6 ", "index_score": "33.3 "}
{"ranking": "413", "school": "齐齐哈尔大学", "local": "黑龙江", "total": "27.5 ", "index_score": "30.0 "}
{"ranking": "413", "school": "许昌学院", "local": "河南", "total": "27.5 ", "index_score": "26.7 "}
{"ranking": "415", "school": "上海电机学院", "local": "上海", "total": "27.4 ", "index_score": "31.8 "}
{"ranking": "416", "school": "安庆师范大学", "local": "安徽", "total": "27.3 ", "index_score": "29.5 "}
{"ranking": "416", "school": "赣南医学院", "local": "江西", "total": "27.3 ", "index_score": "29.3 "}
{"ranking": "416", "school": "惠州学院", "local": "广东", "total": "27.3 ", "index_score": "33.4 "}
{"ranking": "416", "school": "丽水学院", "local": "浙江", "total": "27.3 ", "index_score": "27.4 "}
{"ranking": "420", "school": "佛山科学技术学院", "local": "广东", "total": "27.2 ", "index_score": "31.6 "}
{"ranking": "420", "school": "淮阴工学院", "local": "江苏", "total": "27.2 ", "index_score": "29.3 "}
{"ranking": "420", "school": "曲靖师范学院", "local": "云南", "total": "27.2 ", "index_score": "23.3 "}
{"ranking": "420", "school": "泉州师范学院", "local": "福建", "total": "27.2 ", "index_score": "27.2 "}
{"ranking": "420", "school": "四川理工学院", "local": "四川", "total": "27.2 ", "index_score": "26.7 "}
{"ranking": "420", "school": "忻州师范学院", "local": "山西", "total": "27.2 ", "index_score": "32.0 "}
{"ranking": "426", "school": "吉林医药学院", "local": "吉林", "total": "27.1 ", "index_score": "35.9 "}
{"ranking": "426", "school": "佳木斯大学", "local": "黑龙江", "total": "27.1 ", "index_score": "30.6 "}
{"ranking": "426", "school": "临沂大学", "local": "山东", "total": "27.1 ", "index_score": "23.0 "}
{"ranking": "426", "school": "内蒙古工业大学", "local": "内蒙古", "total": "27.1 ", "index_score": "32.1 "}
{"ranking": "426", "school": "山东工商学院", "local": "山东", "total": "27.1 ", "index_score": "27.1 "}
{"ranking": "426", "school": "新疆大学", "local": "新疆", "total": "27.1 ", "index_score": "25.9 "}
{"ranking": "432", "school": "哈尔滨学院", "local": "黑龙江", "total": "27.0 ", "index_score": "31.4 "}
{"ranking": "432", "school": "河南工程学院", "local": "河南", "total": "27.0 ", "index_score": "34.4 "}
{"ranking": "432", "school": "吉林化工学院", "local": "吉林", "total": "27.0 ", "index_score": "31.3 "}
{"ranking": "432", "school": "江苏理工学院", "local": "江苏", "total": "27.0 ", "index_score": "35.7 "}
{"ranking": "432", "school": "江西中医药大学", "local": "江西", "total": "27.0 ", "index_score": "30.2 "}
{"ranking": "432", "school": "新疆医科大学", "local": "新疆", "total": "27.0 ", "index_score": "28.6 "}
{"ranking": "438", "school": "广西科技大学", "local": "广西", "total": "26.9 ", "index_score": "33.0 "}
{"ranking": "438", "school": "湖南工程学院", "local": "湖南", "total": "26.9 ", "index_score": "30.8 "}
{"ranking": "438", "school": "岭南师范学院", "local": "广东", "total": "26.9 ", "index_score": "29.2 "}
{"ranking": "438", "school": "通化师范学院", "local": "吉林", "total": "26.9 ", "index_score": "35.6 "}
{"ranking": "442", "school": "贵州师范学院", "local": "贵州", "total": "26.8 ", "index_score": "18.2 "}
{"ranking": "442", "school": "衡阳师范学院", "local": "湖南", "total": "26.8 ", "index_score": "29.4 "}
{"ranking": "442", "school": "遵义医学院", "local": "贵州", "total": "26.8 ", "index_score": "30.1 "}
{"ranking": "445", "school": "长江师范学院", "local": "重庆", "total": "26.7 ", "index_score": "26.3 "}
{"ranking": "445", "school": "成都学院", "local": "四川", "total": "26.7 ", "index_score": "29.7 "}
{"ranking": "445", "school": "洛阳理工学院", "local": "河南", "total": "26.7 ", "index_score": "33.9 "}
{"ranking": "445", "school": "商丘师范学院", "local": "河南", "total": "26.7 ", "index_score": "26.3 "}
{"ranking": "445", "school": "湘南学院", "local": "湖南", "total": "26.7 ", "index_score": "29.8 "}
{"ranking": "450", "school": "赣南师范大学", "local": "江西", "total": "26.6 ", "index_score": "25.9 "}
{"ranking": "451", "school": "甘肃农业大学", "local": "甘肃", "total": "26.5 ", "index_score": "29.4 "}
{"ranking": "451", "school": "荆楚理工学院", "local": "湖北", "total": "26.5 ", "index_score": "29.8 "}
{"ranking": "451", "school": "景德镇陶瓷大学", "local": "江西", "total": "26.5 ", "index_score": "21.1 "}
{"ranking": "451", "school": "韶关学院", "local": "广东", "total": "26.5 ", "index_score": "26.3 "}
{"ranking": "455", "school": "韩山师范学院", "local": "广东", "total": "26.4 ", "index_score": "24.9 "}
{"ranking": "455", "school": "湖南城市学院", "local": "湖南", "total": "26.4 ", "index_score": "28.3 "}
{"ranking": "455", "school": "太原师范学院", "local": "山西", "total": "26.4 ", "index_score": "41.4 "}
{"ranking": "455", "school": "咸阳师范学院", "local": "陕西", "total": "26.4 ", "index_score": "33.8 "}
{"ranking": "459", "school": "黄山学院", "local": "安徽", "total": "26.3 ", "index_score": "26.3 "}
{"ranking": "459", "school": "南昌工程学院", "local": "江西", "total": "26.3 ", "index_score": "27.0 "}
{"ranking": "461", "school": "昆明学院", "local": "云南", "total": "26.2 ", "index_score": "24.4 "}
{"ranking": "461", "school": "南京晓庄学院", "local": "江苏", "total": "26.2 ", "index_score": "37.4 "}
{"ranking": "461", "school": "玉溪师范学院", "local": "云南", "total": "26.2 ", "index_score": "21.4 "}
{"ranking": "464", "school": "贵州民族大学", "local": "贵州", "total": "26.1 ", "index_score": "22.0 "}
{"ranking": "464", "school": "华北科技学院", "local": "河北", "total": "26.1 ", "index_score": "33.8 "}
{"ranking": "466", "school": "渭南师范学院", "local": "陕西", "total": "26.0 ", "index_score": "32.3 "}
{"ranking": "467", "school": "鞍山师范学院", "local": "辽宁", "total": "25.9 ", "index_score": "30.2 "}
{"ranking": "468", "school": "重庆三峡学院", "local": "重庆", "total": "25.8 ", "index_score": "27.0 "}
{"ranking": "469", "school": "井冈山大学", "local": "江西", "total": "25.7 ", "index_score": "25.6 "}
{"ranking": "469", "school": "西藏大学", "local": "西藏", "total": "25.7 ", "index_score": "28.3 "}
{"ranking": "471", "school": "北方民族大学", "local": "宁夏", "total": "25.6 ", "index_score": "25.2 "}
{"ranking": "472", "school": "长春工程学院", "local": "吉林", "total": "25.5 ", "index_score": "31.1 "}
{"ranking": "473", "school": "黑龙江八一农垦大学", "local": "黑龙江", "total": "25.4 ", "index_score": "28.9 "}
{"ranking": "474", "school": "黄淮学院", "local": "河南", "total": "25.3 ", "index_score": "26.4 "}
{"ranking": "474", "school": "牡丹江医学院", "local": "黑龙江", "total": "25.3 ", "index_score": "33.7 "}
{"ranking": "476", "school": "安阳工学院", "local": "河南", "total": "25.2 ", "index_score": "31.0 "}
{"ranking": "477", "school": "贵州师范大学", "local": "贵州", "total": "25.1 ", "index_score": "25.4 "}
{"ranking": "477", "school": "榆林学院", "local": "陕西", "total": "25.1 ", "index_score": "29.8 "}
{"ranking": "479", "school": "湖南工学院", "local": "湖南", "total": "24.9 ", "index_score": "26.7 "}
{"ranking": "479", "school": "乐山师范学院", "local": "四川", "total": "24.9 ", "index_score": "19.7 "}
{"ranking": "479", "school": "周口师范学院", "local": "河南", "total": "24.9 ", "index_score": "25.6 "}
{"ranking": "482", "school": "兰州城市学院", "local": "甘肃", "total": "24.7 ", "index_score": "25.5 "}
{"ranking": "482", "school": "内江师范学院", "local": "四川", "total": "24.7 ", "index_score": "18.5 "}
{"ranking": "484", "school": "嘉应学院", "local": "广东", "total": "24.6 ", "index_score": "24.6 "}
{"ranking": "484", "school": "牡丹江师范学院", "local": "黑龙江", "total": "24.6 ", "index_score": "29.1 "}
{"ranking": "484", "school": "皖西学院", "local": "安徽", "total": "24.6 ", "index_score": "22.2 "}
{"ranking": "487", "school": "内蒙古科技大学", "local": "内蒙古", "total": "24.5 ", "index_score": "27.1 "}
{"ranking": "487", "school": "青海师范大学", "local": "青海", "total": "24.5 ", "index_score": "17.6 "}
{"ranking": "489", "school": "南阳理工学院", "local": "河南", "total": "24.4 ", "index_score": "29.6 "}
{"ranking": "490", "school": "山东交通学院", "local": "山东", "total": "24.3 ", "index_score": "22.2 "}
{"ranking": "491", "school": "怀化学院", "local": "湖南", "total": "24.2 ", "index_score": "23.2 "}
{"ranking": "492", "school": "安徽科技学院", "local": "安徽", "total": "24.1 ", "index_score": "20.1 "}
{"ranking": "492", "school": "滁州学院", "local": "安徽", "total": "24.1 ", "index_score": "22.0 "}
{"ranking": "492", "school": "平顶山学院", "local": "河南", "total": "24.1 ", "index_score": "26.9 "}
{"ranking": "492", "school": "四川文理学院", "local": "四川", "total": "24.1 ", "index_score": "17.8 "}
{"ranking": "492", "school": "泰山学院", "local": "山东", "total": "24.1 ", "index_score": "15.9 "}
{"ranking": "492", "school": "浙江万里学院", "local": "浙江", "total": "24.1 ", "index_score": "15.7 "}
{"ranking": "498", "school": "滨州学院", "local": "山东", "total": "24.0 ", "index_score": "16.2 "}
{"ranking": "498", "school": "天津职业技术师范大学", "local": "天津", "total": "24.0 ", "index_score": "31.1 "}
{"ranking": "500", "school": "邵阳学院", "local": "湖南", "total": "23.9 ", "index_score": "23.8 "}
{"ranking": "1", "school": "清华大学", "local": "北京", "total": "94.0 ", "index_score": "100.0 "}
{"ranking": "2", "school": "北京大学", "local": "北京", "total": "81.2 ", "index_score": "96.1 "}
{"ranking": "3", "school": "浙江大学", "local": "浙江", "total": "77.8 ", "index_score": "87.2 "}
{"ranking": "4", "school": "上海交通大学", "local": "上海", "total": "77.5 ", "index_score": "89.4 "}
{"ranking": "5", "school": "复旦大学", "local": "上海", "total": "71.1 ", "index_score": "91.8 "}
{"ranking": "6", "school": "中国科学技术大学", "local": "安徽", "total": "65.9 ", "index_score": "91.9 "}
{"ranking": "7", "school": "南京大学", "local": "江苏", "total": "65.3 ", "index_score": "87.1 "}
{"ranking": "8", "school": "华中科技大学", "local": "湖北", "total": "63.0 ", "index_score": "80.6 "}
{"ranking": "9", "school": "中山大学", "local": "广东", "total": "62.7 ", "index_score": "81.1 "}
{"ranking": "10", "school": "哈尔滨工业大学", "local": "黑龙江", "total": "61.6 ", "index_score": "76.4 "}
{"ranking": "11", "school": "同济大学", "local": "上海", "total": "60.8 ", "index_score": "86.2 "}
{"ranking": "12", "school": "东南大学", "local": "江苏", "total": "59.8 ", "index_score": "80.5 "}
{"ranking": "13", "school": "武汉大学", "local": "湖北", "total": "58.4 ", "index_score": "82.5 "}
{"ranking": "14", "school": "北京航空航天大学", "local": "北京", "total": "58.3 ", "index_score": "85.5 "}
{"ranking": "15", "school": "南开大学", "local": "天津", "total": "58.2 ", "index_score": "86.5 "}
{"ranking": "16", "school": "四川大学", "local": "四川", "total": "57.4 ", "index_score": "74.5 "}
{"ranking": "16", "school": "西安交通大学", "local": "陕西", "total": "57.4 ", "index_score": "82.2 "}
{"ranking": "18", "school": "天津大学", "local": "天津", "total": "56.2 ", "index_score": "82.7 "}
{"ranking": "19", "school": "华南理工大学", "local": "广东", "total": "56.1 ", "index_score": "75.6 "}
{"ranking": "20", "school": "北京师范大学", "local": "北京", "total": "55.1 ", "index_score": "82.5 "}
{"ranking": "21", "school": "厦门大学", "local": "福建", "total": "55.0 ", "index_score": "81.5 "}
{"ranking": "22", "school": "山东大学", "local": "山东", "total": "54.5 ", "index_score": "71.9 "}
{"ranking": "23", "school": "大连理工大学", "local": "辽宁", "total": "54.1 ", "index_score": "74.0 "}
{"ranking": "24", "school": "吉林大学", "local": "吉林", "total": "53.9 ", "index_score": "72.3 "}
{"ranking": "25", "school": "北京理工大学", "local": "北京", "total": "53.1 ", "index_score": "80.4 "}
{"ranking": "26", "school": "中南大学", "local": "湖南", "total": "52.4 ", "index_score": "74.2 "}
{"ranking": "27", "school": "对外经济贸易大学", "local": "北京", "total": "51.9 ", "index_score": "84.5 "}
{"ranking": "28", "school": "苏州大学", "local": "江苏", "total": "51.7 ", "index_score": "65.1 "}
{"ranking": "28", "school": "中国人民大学", "local": "北京", "total": "51.7 ", "index_score": "90.0 "}
{"ranking": "30", "school": "西北工业大学", "local": "陕西", "total": "51.1 ", "index_score": "75.5 "}
{"ranking": "31", "school": "湖南大学", "local": "湖南", "total": "50.7 ", "index_score": "73.3 "}
{"ranking": "32", "school": "华东理工大学", "local": "上海", "total": "50.0 ", "index_score": "70.7 "}
{"ranking": "32", "school": "华东师范大学", "local": "上海", "total": "50.0 ", "index_score": "76.1 "}
{"ranking": "34", "school": "电子科技大学", "local": "四川", "total": "49.4 ", "index_score": "73.3 "}
{"ranking": "35", "school": "重庆大学", "local": "重庆", "total": "49.3 ", "index_score": "72.0 "}
{"ranking": "36", "school": "南京航空航天大学", "local": "江苏", "total": "49.1 ", "index_score": "70.8 "}
{"ranking": "37", "school": "北京科技大学", "local": "北京", "total": "48.9 ", "index_score": "73.2 "}
{"ranking": "38", "school": "上海财经大学", "local": "上海", "total": "48.8 ", "index_score": "84.5 "}
{"ranking": "39", "school": "南京理工大学", "local": "江苏", "total": "48.0 ", "index_score": "70.7 "}
{"ranking": "39", "school": "中国农业大学", "local": "北京", "total": "48.0 ", "index_score": "69.7 "}
{"ranking": "41", "school": "北京交通大学", "local": "北京", "total": "47.4 ", "index_score": "73.4 "}
{"ranking": "42", "school": "北京化工大学", "local": "北京", "total": "47.1 ", "index_score": "65.8 "}
{"ranking": "42", "school": "首都医科大学", "local": "北京", "total": "47.1 ", "index_score": "71.0 "}
{"ranking": "44", "school": "福州大学", "local": "福建", "total": "46.7 ", "index_score": "65.9 "}
{"ranking": "44", "school": "武汉理工大学", "local": "湖北", "total": "46.7 ", "index_score": "67.5 "}
{"ranking": "44", "school": "中央财经大学", "local": "北京", "total": "46.7 ", "index_score": "84.4 "}
{"ranking": "47", "school": "北京邮电大学", "local": "北京", "total": "46.6 ", "index_score": "77.4 "}
{"ranking": "47", "school": "东华大学", "local": "上海", "total": "46.6 ", "index_score": "65.6 "}
{"ranking": "47", "school": "华中师范大学", "local": "湖北", "total": "46.6 ", "index_score": "67.6 "}
{"ranking": "50", "school": "上海大学", "local": "上海", "total": "46.5 ", "index_score": "63.5 "}
{"ranking": "51", "school": "西安电子科技大学", "local": "陕西", "total": "46.2 ", "index_score": "70.3 "}
{"ranking": "52", "school": "北京协和医学院", "local": "北京", "total": "45.9 ", "index_score": "72.4 "}
{"ranking": "53", "school": "天津医科大学", "local": "天津", "total": "45.7 ", "index_score": "71.4 "}
{"ranking": "54", "school": "华北电力大学", "local": "北京", "total": "45.5 ", "index_score": "72.1 "}
{"ranking": "55", "school": "东北大学", "local": "辽宁", "total": "45.3 ", "index_score": "67.2 "}
{"ranking": "55", "school": "东北师范大学", "local": "吉林", "total": "45.3 ", "index_score": "63.7 "}
{"ranking": "57", "school": "暨南大学", "local": "广东", "total": "45.2 ", "index_score": "70.9 "}
{"ranking": "58", "school": "兰州大学", "local": "甘肃", "total": "45.0 ", "index_score": "66.3 "}
{"ranking": "59", "school": "江南大学", "local": "江苏", "total": "44.8 ", "index_score": "65.4 "}
{"ranking": "59", "school": "南京医科大学", "local": "江苏", "total": "44.8 ", "index_score": "60.7 "}
{"ranking": "61", "school": "中国海洋大学", "local": "山东", "total": "44.7 ", "index_score": "69.0 "}
{"ranking": "62", "school": "上海外国语大学", "local": "上海", "total": "44.5 ", "index_score": "75.8 "}
{"ranking": "63", "school": "中国地质大学（北京）", "local": "北京", "total": "44.3 ", "index_score": "63.9 "}
{"ranking": "64", "school": "西南财经大学", "local": "四川", "total": "44.1 ", "index_score": "76.7 "}
{"ranking": "65", "school": "中国地质大学（武汉）", "local": "湖北", "total": "44.0 ", "index_score": "63.5 "}
{"ranking": "66", "school": "华中农业大学", "local": "湖北", "total": "43.9 ", "index_score": "61.4 "}
{"ranking": "66", "school": "南方医科大学", "local": "广东", "total": "43.9 ", "index_score": "64.9 "}
{"ranking": "68", "school": "合肥工业大学", "local": "安徽", "total": "43.6 ", "index_score": "62.7 "}
{"ranking": "69", "school": "中国医科大学", "local": "辽宁", "total": "43.5 ", "index_score": "69.5 "}
{"ranking": "70", "school": "西南大学", "local": "重庆", "total": "43.4 ", "index_score": "59.9 "}
{"ranking": "71", "school": "南京农业大学", "local": "江苏", "total": "43.3 ", "index_score": "60.4 "}
{"ranking": "71", "school": "中国药科大学", "local": "江苏", "total": "43.3 ", "index_score": "66.3 "}
{"ranking": "71", "school": "中南财经政法大学", "local": "湖北", "total": "43.3 ", "index_score": "74.9 "}
{"ranking": "74", "school": "哈尔滨工程大学", "local": "黑龙江", "total": "43.2 ", "index_score": "67.5 "}
{"ranking": "74", "school": "中国石油大学（北京）", "local": "北京", "total": "43.2 ", "index_score": "66.0 "}
{"ranking": "76", "school": "浙江工业大学", "local": "浙江", "total": "43.0 ", "index_score": "64.7 "}
{"ranking": "77", "school": "东北财经大学", "local": "辽宁", "total": "42.9 ", "index_score": "70.3 "}
{"ranking": "77", "school": "河海大学", "local": "江苏", "total": "42.9 ", "index_score": "66.3 "}
{"ranking": "77", "school": "中国矿业大学", "local": "江苏", "total": "42.9 ", "index_score": "60.6 "}
{"ranking": "80", "school": "北京工业大学", "local": "北京", "total": "42.8 ", "index_score": "64.3 "}
{"ranking": "80", "school": "中国石油大学（华东）", "local": "山东", "total": "42.8 ", "index_score": "63.6 "}
{"ranking": "82", "school": "广东外语外贸大学", "local": "广东", "total": "42.7 ", "index_score": "64.3 "}
{"ranking": "83", "school": "南京师范大学", "local": "江苏", "total": "42.4 ", "index_score": "59.2 "}
{"ranking": "84", "school": "中国政法大学", "local": "北京", "total": "42.3 ", "index_score": "80.3 "}
{"ranking": "85", "school": "北京中医药大学", "local": "北京", "total": "42.0 ", "index_score": "68.6 "}
{"ranking": "85", "school": "西南交通大学", "local": "四川", "total": "42.0 ", "index_score": "61.3 "}
{"ranking": "87", "school": "华南师范大学", "local": "广东", "total": "41.9 ", "index_score": "61.8 "}
{"ranking": "87", "school": "中国传媒大学", "local": "北京", "total": "41.9 ", "index_score": "74.4 "}
{"ranking": "89", "school": "北京林业大学", "local": "北京", "total": "41.7 ", "index_score": "66.3 "}
{"ranking": "89", "school": "江苏大学", "local": "江苏", "total": "41.7 ", "index_score": "53.3 "}
{"ranking": "89", "school": "深圳大学", "local": "广东", "total": "41.7 ", "index_score": "57.9 "}
{"ranking": "92", "school": "汕头大学", "local": "广东", "total": "41.6 ", "index_score": "61.1 "}
{"ranking": "92", "school": "首都经济贸易大学", "local": "北京", "total": "41.6 ", "index_score": "63.3 "}
{"ranking": "92", "school": "西北农林科技大学", "local": "陕西", "total": "41.6 ", "index_score": "60.1 "}
{"ranking": "95", "school": "浙江师范大学", "local": "浙江", "total": "41.5 ", "index_score": "57.8 "}
{"ranking": "96", "school": "安徽大学", "local": "安徽", "total": "41.3 ", "index_score": "62.5 "}
{"ranking": "97", "school": "大连医科大学", "local": "辽宁", "total": "41.2 ", "index_score": "61.7 "}
{"ranking": "97", "school": "浙江理工大学", "local": "浙江", "total": "41.2 ", "index_score": "59.2 "}
{"ranking": "99", "school": "南京邮电大学", "local": "江苏", "total": "41.1 ", "index_score": "58.1 "}
{"ranking": "100", "school": "华侨大学", "local": "福建", "total": "41.0 ", "index_score": "58.0 "}
{"ranking": "100", "school": "宁波大学", "local": "浙江", "total": "41.0 ", "index_score": "58.9 "}
{"ranking": "102", "school": "西北大学", "local": "陕西", "total": "40.8 ", "index_score": "63.7 "}
{"ranking": "103", "school": "南京工业大学", "local": "江苏", "total": "40.7 ", "index_score": "53.9 "}
{"ranking": "103", "school": "上海中医药大学", "local": "上海", "total": "40.7 ", "index_score": "53.7 "}
{"ranking": "105", "school": "陕西师范大学", "local": "陕西", "total": "40.3 ", "index_score": "61.8 "}
{"ranking": "105", "school": "首都师范大学", "local": "北京", "total": "40.3 ", "index_score": "57.3 "}
{"ranking": "105", "school": "西交利物浦大学", "local": "江苏", "total": "40.3 ", "index_score": "56.5 "}
{"ranking": "108", "school": "杭州电子科技大学", "local": "浙江", "total": "40.1 ", "index_score": "58.7 "}
{"ranking": "109", "school": "杭州师范大学", "local": "浙江", "total": "40.0 ", "index_score": "53.0 "}
{"ranking": "109", "school": "燕山大学", "local": "河北", "total": "40.0 ", "index_score": "64.0 "}
{"ranking": "111", "school": "大连海事大学", "local": "辽宁", "total": "39.8 ", "index_score": "61.3 "}
{"ranking": "111", "school": "河北工业大学", "local": "河北", "total": "39.8 ", "index_score": "67.4 "}
{"ranking": "111", "school": "南京信息工程大学", "local": "江苏", "total": "39.8 ", "index_score": "52.8 "}
{"ranking": "114", "school": "中央民族大学", "local": "北京", "total": "39.7 ", "index_score": "63.2 "}
{"ranking": "115", "school": "沈阳药科大学", "local": "辽宁", "total": "39.6 ", "index_score": "57.4 "}
{"ranking": "116", "school": "天津财经大学", "local": "天津", "total": "39.5 ", "index_score": "67.9 "}
{"ranking": "117", "school": "哈尔滨医科大学", "local": "黑龙江", "total": "39.3 ", "index_score": "56.5 "}
{"ranking": "118", "school": "浙江工商大学", "local": "浙江", "total": "39.1 ", "index_score": "60.5 "}
{"ranking": "119", "school": "长安大学", "local": "陕西", "total": "39.0 ", "index_score": "63.9 "}
{"ranking": "119", "school": "湘潭大学", "local": "湖南", "total": "39.0 ", "index_score": "55.5 "}
{"ranking": "121", "school": "云南大学", "local": "云南", "total": "38.9 ", "index_score": "56.6 "}
{"ranking": "122", "school": "重庆医科大学", "local": "重庆", "total": "38.7 ", "index_score": "54.7 "}
{"ranking": "122", "school": "南京财经大学", "local": "江苏", "total": "38.7 ", "index_score": "56.7 "}
{"ranking": "122", "school": "上海理工大学", "local": "上海", "total": "38.7 ", "index_score": "57.8 "}
{"ranking": "125", "school": "湖北大学", "local": "湖北", "total": "38.6 ", "index_score": "57.3 "}
{"ranking": "125", "school": "湖南师范大学", "local": "湖南", "total": "38.6 ", "index_score": "61.3 "}
{"ranking": "127", "school": "扬州大学", "local": "江苏", "total": "38.5 ", "index_score": "49.2 "}
{"ranking": "128", "school": "温州医科大学", "local": "浙江", "total": "38.3 ", "index_score": "51.8 "}
{"ranking": "128", "school": "浙江财经大学", "local": "浙江", "total": "38.3 ", "index_score": "57.9 "}
{"ranking": "130", "school": "安徽医科大学", "local": "安徽", "total": "38.2 ", "index_score": "55.7 "}
{"ranking": "130", "school": "福建医科大学", "local": "福建", "total": "38.2 ", "index_score": "58.6 "}
{"ranking": "132", "school": "广东工业大学", "local": "广东", "total": "38.1 ", "index_score": "53.9 "}
{"ranking": "133", "school": "广州医科大学", "local": "广东", "total": "37.9 ", "index_score": "55.0 "}
{"ranking": "133", "school": "河北医科大学", "local": "河北", "total": "37.9 ", "index_score": "58.5 "}
{"ranking": "133", "school": "辽宁大学", "local": "辽宁", "total": "37.9 ", "index_score": "58.2 "}
{"ranking": "133", "school": "上海师范大学", "local": "上海", "total": "37.9 ", "index_score": "48.2 "}
{"ranking": "137", "school": "河北大学", "local": "河北", "total": "37.7 ", "index_score": "60.0 "}
{"ranking": "137", "school": "华南农业大学", "local": "广东", "total": "37.7 ", "index_score": "52.4 "}
{"ranking": "139", "school": "南昌大学", "local": "江西", "total": "37.6 ", "index_score": "51.8 "}
{"ranking": "139", "school": "太原理工大学", "local": "山西", "total": "37.6 ", "index_score": "58.5 "}
{"ranking": "141", "school": "南京审计大学", "local": "江苏", "total": "37.5 ", "index_score": "58.4 "}
{"ranking": "142", "school": "广西大学", "local": "广西", "total": "37.4 ", "index_score": "56.8 "}
{"ranking": "143", "school": "山西大学", "local": "山西", "total": "37.3 ", "index_score": "53.7 "}
{"ranking": "143", "school": "郑州大学", "local": "河南", "total": "37.3 ", "index_score": "44.9 "}
{"ranking": "145", "school": "广西医科大学", "local": "广西", "total": "37.1 ", "index_score": "52.6 "}
{"ranking": "146", "school": "东北林业大学", "local": "黑龙江", "total": "37.0 ", "index_score": "57.7 "}
{"ranking": "147", "school": "东北农业大学", "local": "黑龙江", "total": "36.9 ", "index_score": "54.8 "}
{"ranking": "148", "school": "武汉科技大学", "local": "湖北", "total": "36.8 ", "index_score": "57.8 "}
{"ranking": "149", "school": "石家庄铁道大学", "local": "河北", "total": "36.7 ", "index_score": "59.0 "}
{"ranking": "150", "school": "渤海大学", "local": "辽宁", "total": "36.6 ", "index_score": "37.4 "}
{"ranking": "151", "school": "安徽师范大学", "local": "安徽", "total": "36.4 ", "index_score": "47.3 "}
{"ranking": "152", "school": "长沙理工大学", "local": "湖南", "total": "36.3 ", "index_score": "53.9 "}
{"ranking": "152", "school": "福建师范大学", "local": "福建", "total": "36.3 ", "index_score": "50.0 "}
{"ranking": "152", "school": "黑龙江大学", "local": "黑龙江", "total": "36.3 ", "index_score": "46.8 "}
{"ranking": "152", "school": "江西财经大学", "local": "江西", "total": "36.3 ", "index_score": "55.3 "}
{"ranking": "156", "school": "广州大学", "local": "广东", "total": "36.2 ", "index_score": "52.5 "}
{"ranking": "157", "school": "北京工商大学", "local": "北京", "total": "36.1 ", "index_score": "54.4 "}
{"ranking": "157", "school": "河北师范大学", "local": "河北", "total": "36.1 ", "index_score": "54.4 "}
{"ranking": "157", "school": "三峡大学", "local": "湖北", "total": "36.1 ", "index_score": "50.9 "}
{"ranking": "157", "school": "天津师范大学", "local": "天津", "total": "36.1 ", "index_score": "51.4 "}
{"ranking": "157", "school": "温州大学", "local": "浙江", "total": "36.1 ", "index_score": "45.9 "}
{"ranking": "162", "school": "安徽工业大学", "local": "安徽", "total": "35.9 ", "index_score": "46.9 "}
{"ranking": "162", "school": "河北科技大学", "local": "河北", "total": "35.9 ", "index_score": "53.5 "}
{"ranking": "164", "school": "青岛大学", "local": "山东", "total": "35.8 ", "index_score": "45.9 "}
{"ranking": "165", "school": "辽宁工业大学", "local": "辽宁", "total": "35.7 ", "index_score": "34.3 "}
{"ranking": "165", "school": "上海海事大学", "local": "上海", "total": "35.7 ", "index_score": "48.3 "}
{"ranking": "167", "school": "徐州医科大学", "local": "江苏", "total": "35.6 ", "index_score": "49.8 "}
{"ranking": "168", "school": "天津工业大学", "local": "天津", "total": "35.5 ", "index_score": "47.8 "}
{"ranking": "169", "school": "北京体育大学", "local": "北京", "total": "35.4 ", "index_score": "57.6 "}
{"ranking": "169", "school": "四川农业大学", "local": "四川", "total": "35.4 ", "index_score": "49.1 "}
{"ranking": "171", "school": "西安理工大学", "local": "陕西", "total": "35.3 ", "index_score": "54.1 "}
{"ranking": "172", "school": "河南大学", "local": "河南", "total": "35.2 ", "index_score": "47.0 "}
{"ranking": "172", "school": "武汉工程大学", "local": "湖北", "total": "35.2 ", "index_score": "50.2 "}
{"ranking": "174", "school": "广州中医药大学", "local": "广东", "total": "35.1 ", "index_score": "52.1 "}
{"ranking": "174", "school": "天津中医药大学", "local": "天津", "total": "35.1 ", "index_score": "45.8 "}
{"ranking": "176", "school": "重庆邮电大学", "local": "重庆", "total": "35.0 ", "index_score": "50.9 "}
{"ranking": "176", "school": "济南大学", "local": "山东", "total": "35.0 ", "index_score": "40.2 "}
{"ranking": "176", "school": "闽南师范大学", "local": "福建", "total": "35.0 ", "index_score": "41.0 "}
{"ranking": "179", "school": "北京建筑大学", "local": "北京", "total": "34.9 ", "index_score": "51.4 "}
{"ranking": "180", "school": "重庆工商大学", "local": "重庆", "total": "34.8 ", "index_score": "45.7 "}
{"ranking": "180", "school": "福建农林大学", "local": "福建", "total": "34.8 ", "index_score": "44.7 "}
{"ranking": "180", "school": "青岛科技大学", "local": "山东", "total": "34.8 ", "index_score": "43.9 "}
{"ranking": "180", "school": "沈阳航空航天大学", "local": "辽宁", "total": "34.8 ", "index_score": "46.3 "}
{"ranking": "184", "school": "河北农业大学", "local": "河北", "total": "34.7 ", "index_score": "50.7 "}
{"ranking": "184", "school": "江苏师范大学", "local": "江苏", "total": "34.7 ", "index_score": "40.1 "}
{"ranking": "184", "school": "浙江农林大学", "local": "浙江", "total": "34.7 ", "index_score": "44.6 "}
{"ranking": "187", "school": "北方工业大学", "local": "北京", "total": "34.6 ", "index_score": "48.9 "}
{"ranking": "187", "school": "天津理工大学", "local": "天津", "total": "34.6 ", "index_score": "45.2 "}
{"ranking": "187", "school": "西安建筑科技大学", "local": "陕西", "total": "34.6 ", "index_score": "53.6 "}
{"ranking": "190", "school": "中国计量大学", "local": "浙江", "total": "34.5 ", "index_score": "46.2 "}
{"ranking": "191", "school": "长春理工大学", "local": "吉林", "total": "34.4 ", "index_score": "52.1 "}
{"ranking": "191", "school": "中国民航大学", "local": "天津", "total": "34.4 ", "index_score": "53.9 "}
{"ranking": "191", "school": "中南民族大学", "local": "湖北", "total": "34.4 ", "index_score": "43.4 "}
{"ranking": "194", "school": "福建中医药大学", "local": "福建", "total": "34.3 ", "index_score": "46.1 "}
{"ranking": "194", "school": "海南大学", "local": "海南", "total": "34.3 ", "index_score": "51.0 "}
{"ranking": "194", "school": "集美大学", "local": "福建", "total": "34.3 ", "index_score": "49.6 "}
{"ranking": "194", "school": "南通大学", "local": "江苏", "total": "34.3 ", "index_score": "41.5 "}
{"ranking": "198", "school": "黑龙江中医药大学", "local": "黑龙江", "total": "34.2 ", "index_score": "40.5 "}
{"ranking": "198", "school": "湖南农业大学", "local": "湖南", "total": "34.2 ", "index_score": "43.3 "}
{"ranking": "200", "school": "辽宁师范大学", "local": "辽宁", "total": "34.1 ", "index_score": "48.9 "}
{"ranking": "200", "school": "上海海洋大学", "local": "上海", "total": "34.1 ", "index_score": "40.7 "}
{"ranking": "202", "school": "南京中医药大学", "local": "江苏", "total": "34.0 ", "index_score": "45.1 "}
{"ranking": "202", "school": "宁夏医科大学", "local": "宁夏", "total": "34.0 ", "index_score": "45.7 "}
{"ranking": "202", "school": "浙江中医药大学", "local": "浙江", "total": "34.0 ", "index_score": "44.4 "}
{"ranking": "205", "school": "广西师范大学", "local": "广西", "total": "33.9 ", "index_score": "43.2 "}
{"ranking": "205", "school": "云南师范大学", "local": "云南", "total": "33.9 ", "index_score": "38.3 "}
{"ranking": "207", "school": "山东师范大学", "local": "山东", "total": "33.8 ", "index_score": "47.0 "}
{"ranking": "208", "school": "北京物资学院", "local": "北京", "total": "33.7 ", "index_score": "41.1 "}
{"ranking": "208", "school": "沈阳医学院", "local": "辽宁", "total": "33.7 ", "index_score": "40.9 "}
{"ranking": "210", "school": "河南师范大学", "local": "河南", "total": "33.6 ", "index_score": "42.3 "}
{"ranking": "210", "school": "西南石油大学", "local": "四川", "total": "33.6 ", "index_score": "46.3 "}
{"ranking": "212", "school": "常州大学", "local": "江苏", "total": "33.5 ", "index_score": "43.0 "}
{"ranking": "212", "school": "山西财经大学", "local": "山西", "total": "33.5 ", "index_score": "51.9 "}
{"ranking": "214", "school": "承德医学院", "local": "河北", "total": "33.4 ", "index_score": "51.7 "}
{"ranking": "214", "school": "江西师范大学", "local": "江西", "total": "33.4 ", "index_score": "38.9 "}
{"ranking": "214", "school": "新乡医学院", "local": "河南", "total": "33.4 ", "index_score": "48.2 "}
{"ranking": "214", "school": "延边大学", "local": "吉林", "total": "33.4 ", "index_score": "48.8 "}
{"ranking": "218", "school": "重庆交通大学", "local": "重庆", "total": "33.3 ", "index_score": "48.5 "}
{"ranking": "218", "school": "昆明医科大学", "local": "云南", "total": "33.3 ", "index_score": "44.9 "}
{"ranking": "220", "school": "湖州师范学院", "local": "浙江", "total": "33.2 ", "index_score": "38.9 "}
{"ranking": "220", "school": "山西师范大学", "local": "山西", "total": "33.2 ", "index_score": "47.5 "}
{"ranking": "220", "school": "天津科技大学", "local": "天津", "total": "33.2 ", "index_score": "44.9 "}
{"ranking": "223", "school": "河北经贸大学", "local": "河北", "total": "33.1 ", "index_score": "54.7 "}
{"ranking": "223", "school": "内蒙古大学", "local": "内蒙古", "total": "33.1 ", "index_score": "46.4 "}
{"ranking": "223", "school": "信阳师范学院", "local": "河南", "total": "33.1 ", "index_score": "36.1 "}
{"ranking": "226", "school": "长江大学", "local": "湖北", "total": "33.0 ", "index_score": "45.3 "}
{"ranking": "226", "school": "河南理工大学", "local": "河南", "total": "33.0 ", "index_score": "44.2 "}
{"ranking": "226", "school": "南华大学", "local": "湖南", "total": "33.0 ", "index_score": "46.1 "}
{"ranking": "226", "school": "武汉轻工大学", "local": "湖北", "total": "33.0 ", "index_score": "42.8 "}
{"ranking": "230", "school": "广东医科大学", "local": "广东", "total": "32.9 ", "index_score": "39.3 "}
{"ranking": "230", "school": "河北北方学院", "local": "河北", "total": "32.9 ", "index_score": "45.2 "}
{"ranking": "230", "school": "上海立信会计学院", "local": "上海", "total": "32.9 ", "index_score": "49.3 "}
{"ranking": "233", "school": "广东药科大学", "local": "广东", "total": "32.8 ", "index_score": "39.9 "}
{"ranking": "233", "school": "山东科技大学", "local": "山东", "total": "32.8 ", "index_score": "42.8 "}
{"ranking": "233", "school": "苏州科技大学", "local": "江苏", "total": "32.8 ", "index_score": "40.1 "}
{"ranking": "236", "school": "北京信息科技大学", "local": "北京", "total": "32.7 ", "index_score": "46.4 "}
{"ranking": "236", "school": "黄冈师范学院", "local": "湖北", "total": "32.7 ", "index_score": "34.1 "}
{"ranking": "238", "school": "湖南科技大学", "local": "湖南", "total": "32.6 ", "index_score": "46.8 "}
{"ranking": "238", "school": "陕西科技大学", "local": "陕西", "total": "32.6 ", "index_score": "48.1 "}
{"ranking": "240", "school": "重庆师范大学", "local": "重庆", "total": "32.5 ", "index_score": "40.9 "}
{"ranking": "240", "school": "湖南工业大学", "local": "湖南", "total": "32.5 ", "index_score": "38.4 "}
{"ranking": "240", "school": "江汉大学", "local": "湖北", "total": "32.5 ", "index_score": "45.2 "}
{"ranking": "240", "school": "江苏科技大学", "local": "江苏", "total": "32.5 ", "index_score": "46.5 "}
{"ranking": "240", "school": "中南林业科技大学", "local": "湖南", "total": "32.5 ", "index_score": "46.6 "}
{"ranking": "245", "school": "东北电力大学", "local": "吉林", "total": "32.4 ", "index_score": "49.3 "}
{"ranking": "245", "school": "山东财经大学", "local": "山东", "total": "32.4 ", "index_score": "49.9 "}
{"ranking": "247", "school": "华北理工大学", "local": "河北", "total": "32.3 ", "index_score": "47.2 "}
{"ranking": "247", "school": "山东农业大学", "local": "山东", "total": "32.3 ", "index_score": "35.0 "}
{"ranking": "247", "school": "西南医科大学", "local": "四川", "total": "32.3 ", "index_score": "44.5 "}
{"ranking": "247", "school": "中北大学", "local": "山西", "total": "32.3 ", "index_score": "49.8 "}
{"ranking": "251", "school": "成都理工大学", "local": "四川", "total": "32.2 ", "index_score": "44.2 "}
{"ranking": "251", "school": "广东财经大学", "local": "广东", "total": "32.2 ", "index_score": "47.1 "}
{"ranking": "251", "school": "西安邮电大学", "local": "陕西", "total": "32.2 ", "index_score": "48.5 "}
{"ranking": "251", "school": "浙江科技学院", "local": "浙江", "total": "32.2 ", "index_score": "40.7 "}
{"ranking": "255", "school": "安徽农业大学", "local": "安徽", "total": "32.0 ", "index_score": "40.5 "}
{"ranking": "255", "school": "昆明理工大学", "local": "云南", "total": "32.0 ", "index_score": "39.1 "}
{"ranking": "255", "school": "宁夏大学", "local": "宁夏", "total": "32.0 ", "index_score": "43.5 "}
{"ranking": "258", "school": "锦州医科大学", "local": "辽宁", "total": "31.8 ", "index_score": "39.7 "}
{"ranking": "258", "school": "烟台大学", "local": "山东", "total": "31.8 ", "index_score": "35.3 "}
{"ranking": "260", "school": "贵州大学", "local": "贵州", "total": "31.7 ", "index_score": "42.8 "}
{"ranking": "260", "school": "吉林师范大学", "local": "吉林", "total": "31.7 ", "index_score": "45.3 "}
{"ranking": "260", "school": "山西医科大学", "local": "山西", "total": "31.7 ", "index_score": "48.8 "}
{"ranking": "260", "school": "绍兴文理学院", "local": "浙江", "total": "31.7 ", "index_score": "38.6 "}
{"ranking": "260", "school": "沈阳农业大学", "local": "辽宁", "total": "31.7 ", "index_score": "46.4 "}
{"ranking": "265", "school": "广西民族大学", "local": "广西", "total": "31.6 ", "index_score": "36.5 "}
{"ranking": "265", "school": "兰州交通大学", "local": "甘肃", "total": "31.6 ", "index_score": "43.0 "}
{"ranking": "265", "school": "闽江学院", "local": "福建", "total": "31.6 ", "index_score": "34.8 "}
{"ranking": "265", "school": "沈阳建筑大学", "local": "辽宁", "total": "31.6 ", "index_score": "49.2 "}
{"ranking": "265", "school": "西北师范大学", "local": "甘肃", "total": "31.6 ", "index_score": "40.2 "}
{"ranking": "270", "school": "大连交通大学", "local": "辽宁", "total": "31.5 ", "index_score": "47.6 "}
{"ranking": "270", "school": "湖北师范大学", "local": "湖北", "total": "31.5 ", "index_score": "38.3 "}
{"ranking": "270", "school": "南京林业大学", "local": "江苏", "total": "31.5 ", "index_score": "36.3 "}
{"ranking": "270", "school": "青岛理工大学", "local": "山东", "total": "31.5 ", "index_score": "42.6 "}
{"ranking": "270", "school": "上海电力学院", "local": "上海", "total": "31.5 ", "index_score": "37.0 "}
{"ranking": "275", "school": "广东技术师范学院", "local": "广东", "total": "31.4 ", "index_score": "39.0 "}
{"ranking": "275", "school": "河南科技大学", "local": "河南", "total": "31.4 ", "index_score": "40.4 "}
{"ranking": "275", "school": "淮北师范大学", "local": "安徽", "total": "31.4 ", "index_score": "33.1 "}
{"ranking": "275", "school": "辽宁中医药大学", "local": "辽宁", "total": "31.4 ", "index_score": "40.4 "}
{"ranking": "275", "school": "上海第二工业大学", "local": "上海", "total": "31.4 ", "index_score": "35.0 "}
{"ranking": "275", "school": "沈阳师范大学", "local": "辽宁", "total": "31.4 ", "index_score": "39.1 "}
{"ranking": "281", "school": "哈尔滨师范大学", "local": "黑龙江", "total": "31.3 ", "index_score": "42.9 "}
{"ranking": "281", "school": "沈阳工业大学", "local": "辽宁", "total": "31.3 ", "index_score": "45.4 "}
{"ranking": "281", "school": "厦门理工学院", "local": "福建", "total": "31.3 ", "index_score": "41.3 "}
{"ranking": "284", "school": "常熟理工学院", "local": "江苏", "total": "31.2 ", "index_score": "34.8 "}
{"ranking": "284", "school": "哈尔滨理工大学", "local": "黑龙江", "total": "31.2 ", "index_score": "44.2 "}
{"ranking": "284", "school": "河南工业大学", "local": "河南", "total": "31.2 ", "index_score": "40.9 "}
{"ranking": "287", "school": "桂林电子科技大学", "local": "广西", "total": "31.1 ", "index_score": "39.8 "}
{"ranking": "287", "school": "兰州理工大学", "local": "甘肃", "total": "31.1 ", "index_score": "38.5 "}
{"ranking": "287", "school": "浙江海洋大学", "local": "浙江", "total": "31.1 ", "index_score": "38.2 "}
{"ranking": "290", "school": "大连大学", "local": "辽宁", "total": "31.0 ", "index_score": "41.1 "}
{"ranking": "290", "school": "河北地质大学", "local": "河北", "total": "31.0 ", "index_score": "42.4 "}
{"ranking": "290", "school": "西华师范大学", "local": "四川", "total": "31.0 ", "index_score": "29.5 "}
{"ranking": "293", "school": "大连海洋大学", "local": "辽宁", "total": "30.9 ", "index_score": "37.9 "}
{"ranking": "293", "school": "大连民族大学", "local": "辽宁", "total": "30.9 ", "index_score": "38.2 "}
{"ranking": "293", "school": "曲阜师范大学", "local": "山东", "total": "30.9 ", "index_score": "32.1 "}
{"ranking": "293", "school": "唐山学院", "local": "河北", "total": "30.9 ", "index_score": "46.8 "}
{"ranking": "297", "school": "广东海洋大学", "local": "广东", "total": "30.8 ", "index_score": "35.1 "}
{"ranking": "297", "school": "河北工程大学", "local": "河北", "total": "30.8 ", "index_score": "44.7 "}
{"ranking": "297", "school": "河南农业大学", "local": "河南", "total": "30.8 ", "index_score": "37.8 "}
{"ranking": "297", "school": "嘉兴学院", "local": "浙江", "total": "30.8 ", "index_score": "35.7 "}
{"ranking": "297", "school": "石家庄学院", "local": "河北", "total": "30.8 ", "index_score": "45.4 "}
{"ranking": "302", "school": "海南医学院", "local": "海南", "total": "30.6 ", "index_score": "35.6 "}
{"ranking": "302", "school": "河南中医药大学", "local": "河南", "total": "30.6 ", "index_score": "42.4 "}
{"ranking": "302", "school": "淮阴师范学院", "local": "江苏", "total": "30.6 ", "index_score": "29.7 "}
{"ranking": "302", "school": "上海应用技术大学", "local": "上海", "total": "30.6 ", "index_score": "31.3 "}
{"ranking": "302", "school": "郑州航空工业管理学院", "local": "河南", "total": "30.6 ", "index_score": "39.7 "}
{"ranking": "307", "school": "大连工业大学", "local": "辽宁", "total": "30.5 ", "index_score": "39.2 "}
{"ranking": "307", "school": "辽宁工程技术大学", "local": "辽宁", "total": "30.5 ", "index_score": "44.7 "}
{"ranking": "307", "school": "太原科技大学", "local": "山西", "total": "30.5 ", "index_score": "43.6 "}
{"ranking": "307", "school": "郑州师范学院", "local": "河南", "total": "30.5 ", "index_score": "32.5 "}
{"ranking": "311", "school": "大理大学", "local": "云南", "total": "30.4 ", "index_score": "29.7 "}
{"ranking": "311", "school": "桂林理工大学", "local": "广西", "total": "30.4 ", "index_score": "36.4 "}
{"ranking": "311", "school": "桂林医学院", "local": "广西", "total": "30.4 ", "index_score": "38.0 "}
{"ranking": "311", "school": "上海工程技术大学", "local": "上海", "total": "30.4 ", "index_score": "37.5 "}
{"ranking": "311", "school": "石河子大学", "local": "新疆", "total": "30.4 ", "index_score": "37.7 "}
{"ranking": "316", "school": "北京印刷学院", "local": "北京", "total": "30.3 ", "index_score": "38.8 "}
{"ranking": "316", "school": "长春工业大学", "local": "吉林", "total": "30.3 ", "index_score": "42.4 "}
{"ranking": "316", "school": "成都中医药大学", "local": "四川", "total": "30.3 ", "index_score": "37.3 "}
{"ranking": "316", "school": "海南师范大学", "local": "海南", "total": "30.3 ", "index_score": "33.0 "}
{"ranking": "320", "school": "长春大学", "local": "吉林", "total": "30.2 ", "index_score": "40.1 "}
{"ranking": "320", "school": "广西中医药大学", "local": "广西", "total": "30.2 ", "index_score": "40.1 "}
{"ranking": "320", "school": "四川师范大学", "local": "四川", "total": "30.2 ", "index_score": "35.8 "}
{"ranking": "320", "school": "唐山师范学院", "local": "河北", "total": "30.2 ", "index_score": "41.8 "}
{"ranking": "324", "school": "华东交通大学", "local": "江西", "total": "30.1 ", "index_score": "42.0 "}
{"ranking": "324", "school": "吉首大学", "local": "湖南", "total": "30.1 ", "index_score": "36.0 "}
{"ranking": "324", "school": "南昌航空大学", "local": "江西", "total": "30.1 ", "index_score": "36.3 "}
{"ranking": "324", "school": "西南民族大学", "local": "四川", "total": "30.1 ", "index_score": "34.1 "}
{"ranking": "328", "school": "安徽理工大学", "local": "安徽", "total": "30.0 ", "index_score": "39.0 "}
{"ranking": "328", "school": "安阳师范学院", "local": "河南", "total": "30.0 ", "index_score": "29.3 "}
{"ranking": "328", "school": "川北医学院", "local": "四川", "total": "30.0 ", "index_score": "37.0 "}
{"ranking": "328", "school": "东北石油大学", "local": "黑龙江", "total": "30.0 ", "index_score": "49.8 "}
{"ranking": "328", "school": "福建工程学院", "local": "福建", "total": "30.0 ", "index_score": "37.8 "}
{"ranking": "328", "school": "哈尔滨商业大学", "local": "黑龙江", "total": "30.0 ", "index_score": "44.6 "}
{"ranking": "328", "school": "天津商业大学", "local": "天津", "total": "30.0 ", "index_score": "42.3 "}
{"ranking": "335", "school": "长治医学院", "local": "山西", "total": "29.9 ", "index_score": "42.2 "}
{"ranking": "335", "school": "湖北工程学院", "local": "湖北", "total": "29.9 ", "index_score": "36.1 "}
{"ranking": "335", "school": "西安财经学院", "local": "陕西", "total": "29.9 ", "index_score": "43.2 "}
{"ranking": "335", "school": "西安石油大学", "local": "陕西", "total": "29.9 ", "index_score": "43.5 "}
{"ranking": "339", "school": "广西师范学院", "local": "广西", "total": "29.8 ", "index_score": "36.5 "}
{"ranking": "339", "school": "宁波工程学院", "local": "浙江", "total": "29.8 ", "index_score": "32.8 "}
{"ranking": "341", "school": "廊坊师范学院", "local": "河北", "total": "29.7 ", "index_score": "43.2 "}
{"ranking": "342", "school": "东莞理工学院", "local": "广东", "total": "29.6 ", "index_score": "35.7 "}
{"ranking": "342", "school": "湖南理工学院", "local": "湖南", "total": "29.6 ", "index_score": "32.4 "}
{"ranking": "342", "school": "西南科技大学", "local": "四川", "total": "29.6 ", "index_score": "39.5 "}
{"ranking": "345", "school": "蚌埠医学院", "local": "安徽", "total": "29.5 ", "index_score": "36.3 "}
{"ranking": "345", "school": "齐齐哈尔医学院", "local": "黑龙江", "total": "29.5 ", "index_score": "33.2 "}
{"ranking": "345", "school": "山西农业大学", "local": "山西", "total": "29.5 ", "index_score": "40.1 "}
{"ranking": "348", "school": "长春师范大学", "local": "吉林", "total": "29.4 ", "index_score": "39.5 "}
{"ranking": "348", "school": "五邑大学", "local": "广东", "total": "29.4 ", "index_score": "34.6 "}
{"ranking": "350", "school": "潍坊医学院", "local": "山东", "total": "29.2 ", "index_score": "33.3 "}
{"ranking": "351", "school": "成都信息工程大学", "local": "四川", "total": "29.1 ", "index_score": "37.5 "}
{"ranking": "351", "school": "湖北汽车工业学院", "local": "湖北", "total": "29.1 ", "index_score": "38.4 "}
{"ranking": "351", "school": "吉林农业大学", "local": "吉林", "total": "29.1 ", "index_score": "33.1 "}
{"ranking": "351", "school": "山东中医药大学", "local": "山东", "total": "29.1 ", "index_score": "33.2 "}
{"ranking": "351", "school": "沈阳理工大学", "local": "辽宁", "total": "29.1 ", "index_score": "42.7 "}
{"ranking": "356", "school": "吉林建筑大学", "local": "吉林", "total": "29.0 ", "index_score": "38.3 "}
{"ranking": "356", "school": "内蒙古医科大学", "local": "内蒙古", "total": "29.0 ", "index_score": "37.9 "}
{"ranking": "356", "school": "山东理工大学", "local": "山东", "total": "29.0 ", "index_score": "34.2 "}
{"ranking": "356", "school": "盐城工学院", "local": "江苏", "total": "29.0 ", "index_score": "31.9 "}
{"ranking": "360", "school": "滨州医学院", "local": "山东", "total": "28.9 ", "index_score": "32.0 "}
{"ranking": "360", "school": "济宁医学院", "local": "山东", "total": "28.9 ", "index_score": "25.5 "}
{"ranking": "360", "school": "山西大同大学", "local": "山西", "total": "28.9 ", "index_score": "39.1 "}
{"ranking": "360", "school": "沈阳大学", "local": "辽宁", "total": "28.9 ", "index_score": "35.7 "}
{"ranking": "360", "school": "西安工程大学", "local": "陕西", "total": "28.9 ", "index_score": "39.7 "}
{"ranking": "360", "school": "西华大学", "local": "四川", "total": "28.9 ", "index_score": "36.8 "}
{"ranking": "360", "school": "延安大学", "local": "陕西", "total": "28.9 ", "index_score": "39.4 "}
{"ranking": "367", "school": "辽宁科技大学", "local": "辽宁", "total": "28.8 ", "index_score": "35.4 "}
{"ranking": "367", "school": "辽宁石油化工大学", "local": "辽宁", "total": "28.8 ", "index_score": "36.9 "}
{"ranking": "367", "school": "陕西理工大学", "local": "陕西", "total": "28.8 ", "index_score": "35.2 "}
{"ranking": "367", "school": "沈阳工程学院", "local": "辽宁", "total": "28.8 ", "index_score": "36.7 "}
{"ranking": "367", "school": "玉林师范学院", "local": "广西", "total": "28.8 ", "index_score": "28.8 "}
{"ranking": "372", "school": "长沙学院", "local": "湖南", "total": "28.7 ", "index_score": "33.3 "}
{"ranking": "372", "school": "湖北理工学院", "local": "湖北", "total": "28.7 ", "index_score": "36.7 "}
{"ranking": "372", "school": "山东建筑大学", "local": "山东", "total": "28.7 ", "index_score": "35.6 "}
{"ranking": "372", "school": "泰山医学院", "local": "山东", "total": "28.7 ", "index_score": "27.3 "}
{"ranking": "372", "school": "天津城建大学", "local": "天津", "total": "28.7 ", "index_score": "38.1 "}
{"ranking": "372", "school": "皖南医学院", "local": "安徽", "total": "28.7 ", "index_score": "31.8 "}
{"ranking": "372", "school": "徐州工程学院", "local": "江苏", "total": "28.7 ", "index_score": "31.1 "}
{"ranking": "379", "school": "湖南商学院", "local": "湖南", "total": "28.6 ", "index_score": "41.7 "}
{"ranking": "380", "school": "北京联合大学", "local": "北京", "total": "28.5 ", "index_score": "29.9 "}
{"ranking": "380", "school": "北京石油化工学院", "local": "北京", "total": "28.5 ", "index_score": "33.6 "}
{"ranking": "380", "school": "东华理工大学", "local": "江西", "total": "28.5 ", "index_score": "29.1 "}
{"ranking": "380", "school": "江西科技师范大学", "local": "江西", "total": "28.5 ", "index_score": "28.3 "}
{"ranking": "380", "school": "青海大学", "local": "青海", "total": "28.5 ", "index_score": "37.3 "}
{"ranking": "385", "school": "河南科技学院", "local": "河南", "total": "28.4 ", "index_score": "32.9 "}
{"ranking": "386", "school": "聊城大学", "local": "山东", "total": "28.3 ", "index_score": "23.1 "}
{"ranking": "386", "school": "南阳师范学院", "local": "河南", "total": "28.3 ", "index_score": "28.4 "}
{"ranking": "388", "school": "贵州医科大学", "local": "贵州", "total": "28.2 ", "index_score": "31.4 "}
{"ranking": "388", "school": "金陵科技学院", "local": "江苏", "total": "28.2 ", "index_score": "37.6 "}
{"ranking": "388", "school": "龙岩学院", "local": "福建", "total": "28.2 ", "index_score": "24.6 "}
{"ranking": "388", "school": "鲁东大学", "local": "山东", "total": "28.2 ", "index_score": "29.9 "}
{"ranking": "388", "school": "盐城师范学院", "local": "江苏", "total": "28.2 ", "index_score": "29.5 "}
{"ranking": "388", "school": "中原工学院", "local": "河南", "total": "28.2 ", "index_score": "33.1 "}
{"ranking": "394", "school": "北京服装学院", "local": "北京", "total": "28.1 ", "index_score": "34.7 "}
{"ranking": "394", "school": "肇庆学院", "local": "广东", "total": "28.1 ", "index_score": "29.8 "}
{"ranking": "396", "school": "天津农学院", "local": "天津", "total": "28.0 ", "index_score": "31.1 "}
{"ranking": "397", "school": "江西农业大学", "local": "江西", "total": "27.9 ", "index_score": "30.1 "}
{"ranking": "397", "school": "太原工业学院", "local": "山西", "total": "27.9 ", "index_score": "39.6 "}
{"ranking": "397", "school": "云南农业大学", "local": "云南", "total": "27.9 ", "index_score": "27.4 "}
{"ranking": "400", "school": "湖南文理学院", "local": "湖南", "total": "27.8 ", "index_score": "28.3 "}
{"ranking": "400", "school": "华北水利水电大学", "local": "河南", "total": "27.8 ", "index_score": "40.1 "}
{"ranking": "400", "school": "江西理工大学", "local": "江西", "total": "27.8 ", "index_score": "31.9 "}
{"ranking": "400", "school": "洛阳师范学院", "local": "河南", "total": "27.8 ", "index_score": "30.7 "}
{"ranking": "400", "school": "莆田学院", "local": "福建", "total": "27.8 ", "index_score": "30.7 "}
{"ranking": "400", "school": "齐鲁工业大学", "local": "山东", "total": "27.8 ", "index_score": "24.3 "}
{"ranking": "400", "school": "青岛农业大学", "local": "山东", "total": "27.8 ", "index_score": "24.0 "}
{"ranking": "400", "school": "西南林业大学", "local": "云南", "total": "27.8 ", "index_score": "29.5 "}
{"ranking": "408", "school": "宝鸡文理学院", "local": "陕西", "total": "27.7 ", "index_score": "34.8 "}
{"ranking": "408", "school": "成都医学院", "local": "四川", "total": "27.7 ", "index_score": "30.7 "}
{"ranking": "408", "school": "淮海工学院", "local": "江苏", "total": "27.7 ", "index_score": "31.5 "}
{"ranking": "411", "school": "北华大学", "local": "吉林", "total": "27.6 ", "index_score": "37.3 "}
{"ranking": "411", "school": "重庆科技学院", "local": "重庆", "total": "27.6 ", "index_score": "33.3 "}
{"ranking": "413", "school": "齐齐哈尔大学", "local": "黑龙江", "total": "27.5 ", "index_score": "30.0 "}
{"ranking": "413", "school": "许昌学院", "local": "河南", "total": "27.5 ", "index_score": "26.7 "}
{"ranking": "415", "school": "上海电机学院", "local": "上海", "total": "27.4 ", "index_score": "31.8 "}
{"ranking": "416", "school": "安庆师范大学", "local": "安徽", "total": "27.3 ", "index_score": "29.5 "}
{"ranking": "416", "school": "赣南医学院", "local": "江西", "total": "27.3 ", "index_score": "29.3 "}
{"ranking": "416", "school": "惠州学院", "local": "广东", "total": "27.3 ", "index_score": "33.4 "}
{"ranking": "416", "school": "丽水学院", "local": "浙江", "total": "27.3 ", "index_score": "27.4 "}
{"ranking": "420", "school": "佛山科学技术学院", "local": "广东", "total": "27.2 ", "index_score": "31.6 "}
{"ranking": "420", "school": "淮阴工学院", "local": "江苏", "total": "27.2 ", "index_score": "29.3 "}
{"ranking": "420", "school": "曲靖师范学院", "local": "云南", "total": "27.2 ", "index_score": "23.3 "}
{"ranking": "420", "school": "泉州师范学院", "local": "福建", "total": "27.2 ", "index_score": "27.2 "}
{"ranking": "420", "school": "四川理工学院", "local": "四川", "total": "27.2 ", "index_score": "26.7 "}
{"ranking": "420", "school": "忻州师范学院", "local": "山西", "total": "27.2 ", "index_score": "32.0 "}
{"ranking": "426", "school": "吉林医药学院", "local": "吉林", "total": "27.1 ", "index_score": "35.9 "}
{"ranking": "426", "school": "佳木斯大学", "local": "黑龙江", "total": "27.1 ", "index_score": "30.6 "}
{"ranking": "426", "school": "临沂大学", "local": "山东", "total": "27.1 ", "index_score": "23.0 "}
{"ranking": "426", "school": "内蒙古工业大学", "local": "内蒙古", "total": "27.1 ", "index_score": "32.1 "}
{"ranking": "426", "school": "山东工商学院", "local": "山东", "total": "27.1 ", "index_score": "27.1 "}
{"ranking": "426", "school": "新疆大学", "local": "新疆", "total": "27.1 ", "index_score": "25.9 "}
{"ranking": "432", "school": "哈尔滨学院", "local": "黑龙江", "total": "27.0 ", "index_score": "31.4 "}
{"ranking": "432", "school": "河南工程学院", "local": "河南", "total": "27.0 ", "index_score": "34.4 "}
{"ranking": "432", "school": "吉林化工学院", "local": "吉林", "total": "27.0 ", "index_score": "31.3 "}
{"ranking": "432", "school": "江苏理工学院", "local": "江苏", "total": "27.0 ", "index_score": "35.7 "}
{"ranking": "432", "school": "江西中医药大学", "local": "江西", "total": "27.0 ", "index_score": "30.2 "}
{"ranking": "432", "school": "新疆医科大学", "local": "新疆", "total": "27.0 ", "index_score": "28.6 "}
{"ranking": "438", "school": "广西科技大学", "local": "广西", "total": "26.9 ", "index_score": "33.0 "}
{"ranking": "438", "school": "湖南工程学院", "local": "湖南", "total": "26.9 ", "index_score": "30.8 "}
{"ranking": "438", "school": "岭南师范学院", "local": "广东", "total": "26.9 ", "index_score": "29.2 "}
{"ranking": "438", "school": "通化师范学院", "local": "吉林", "total": "26.9 ", "index_score": "35.6 "}
{"ranking": "442", "school": "贵州师范学院", "local": "贵州", "total": "26.8 ", "index_score": "18.2 "}
{"ranking": "442", "school": "衡阳师范学院", "local": "湖南", "total": "26.8 ", "index_score": "29.4 "}
{"ranking": "442", "school": "遵义医学院", "local": "贵州", "total": "26.8 ", "index_score": "30.1 "}
{"ranking": "445", "school": "长江师范学院", "local": "重庆", "total": "26.7 ", "index_score": "26.3 "}
{"ranking": "445", "school": "成都学院", "local": "四川", "total": "26.7 ", "index_score": "29.7 "}
{"ranking": "445", "school": "洛阳理工学院", "local": "河南", "total": "26.7 ", "index_score": "33.9 "}
{"ranking": "445", "school": "商丘师范学院", "local": "河南", "total": "26.7 ", "index_score": "26.3 "}
{"ranking": "445", "school": "湘南学院", "local": "湖南", "total": "26.7 ", "index_score": "29.8 "}
{"ranking": "450", "school": "赣南师范大学", "local": "江西", "total": "26.6 ", "index_score": "25.9 "}
{"ranking": "451", "school": "甘肃农业大学", "local": "甘肃", "total": "26.5 ", "index_score": "29.4 "}
{"ranking": "451", "school": "荆楚理工学院", "local": "湖北", "total": "26.5 ", "index_score": "29.8 "}
{"ranking": "451", "school": "景德镇陶瓷大学", "local": "江西", "total": "26.5 ", "index_score": "21.1 "}
{"ranking": "451", "school": "韶关学院", "local": "广东", "total": "26.5 ", "index_score": "26.3 "}
{"ranking": "455", "school": "韩山师范学院", "local": "广东", "total": "26.4 ", "index_score": "24.9 "}
{"ranking": "455", "school": "湖南城市学院", "local": "湖南", "total": "26.4 ", "index_score": "28.3 "}
{"ranking": "455", "school": "太原师范学院", "local": "山西", "total": "26.4 ", "index_score": "41.4 "}
{"ranking": "455", "school": "咸阳师范学院", "local": "陕西", "total": "26.4 ", "index_score": "33.8 "}
{"ranking": "459", "school": "黄山学院", "local": "安徽", "total": "26.3 ", "index_score": "26.3 "}
{"ranking": "459", "school": "南昌工程学院", "local": "江西", "total": "26.3 ", "index_score": "27.0 "}
{"ranking": "461", "school": "昆明学院", "local": "云南", "total": "26.2 ", "index_score": "24.4 "}
{"ranking": "461", "school": "南京晓庄学院", "local": "江苏", "total": "26.2 ", "index_score": "37.4 "}
{"ranking": "461", "school": "玉溪师范学院", "local": "云南", "total": "26.2 ", "index_score": "21.4 "}
{"ranking": "464", "school": "贵州民族大学", "local": "贵州", "total": "26.1 ", "index_score": "22.0 "}
{"ranking": "464", "school": "华北科技学院", "local": "河北", "total": "26.1 ", "index_score": "33.8 "}
{"ranking": "466", "school": "渭南师范学院", "local": "陕西", "total": "26.0 ", "index_score": "32.3 "}
{"ranking": "467", "school": "鞍山师范学院", "local": "辽宁", "total": "25.9 ", "index_score": "30.2 "}
{"ranking": "468", "school": "重庆三峡学院", "local": "重庆", "total": "25.8 ", "index_score": "27.0 "}
{"ranking": "469", "school": "井冈山大学", "local": "江西", "total": "25.7 ", "index_score": "25.6 "}
{"ranking": "469", "school": "西藏大学", "local": "西藏", "total": "25.7 ", "index_score": "28.3 "}
{"ranking": "471", "school": "北方民族大学", "local": "宁夏", "total": "25.6 ", "index_score": "25.2 "}
{"ranking": "472", "school": "长春工程学院", "local": "吉林", "total": "25.5 ", "index_score": "31.1 "}
{"ranking": "473", "school": "黑龙江八一农垦大学", "local": "黑龙江", "total": "25.4 ", "index_score": "28.9 "}
{"ranking": "474", "school": "黄淮学院", "local": "河南", "total": "25.3 ", "index_score": "26.4 "}
{"ranking": "474", "school": "牡丹江医学院", "local": "黑龙江", "total": "25.3 ", "index_score": "33.7 "}
{"ranking": "476", "school": "安阳工学院", "local": "河南", "total": "25.2 ", "index_score": "31.0 "}
{"ranking": "477", "school": "贵州师范大学", "local": "贵州", "total": "25.1 ", "index_score": "25.4 "}
{"ranking": "477", "school": "榆林学院", "local": "陕西", "total": "25.1 ", "index_score": "29.8 "}
{"ranking": "479", "school": "湖南工学院", "local": "湖南", "total": "24.9 ", "index_score": "26.7 "}
{"ranking": "479", "school": "乐山师范学院", "local": "四川", "total": "24.9 ", "index_score": "19.7 "}
{"ranking": "479", "school": "周口师范学院", "local": "河南", "total": "24.9 ", "index_score": "25.6 "}
{"ranking": "482", "school": "兰州城市学院", "local": "甘肃", "total": "24.7 ", "index_score": "25.5 "}
{"ranking": "482", "school": "内江师范学院", "local": "四川", "total": "24.7 ", "index_score": "18.5 "}
{"ranking": "484", "school": "嘉应学院", "local": "广东", "total": "24.6 ", "index_score": "24.6 "}
{"ranking": "484", "school": "牡丹江师范学院", "local": "黑龙江", "total": "24.6 ", "index_score": "29.1 "}
{"ranking": "484", "school": "皖西学院", "local": "安徽", "total": "24.6 ", "index_score": "22.2 "}
{"ranking": "487", "school": "内蒙古科技大学", "local": "内蒙古", "total": "24.5 ", "index_score": "27.1 "}
{"ranking": "487", "school": "青海师范大学", "local": "青海", "total": "24.5 ", "index_score": "17.6 "}
{"ranking": "489", "school": "南阳理工学院", "local": "河南", "total": "24.4 ", "index_score": "29.6 "}
{"ranking": "490", "school": "山东交通学院", "local": "山东", "total": "24.3 ", "index_score": "22.2 "}
{"ranking": "491", "school": "怀化学院", "local": "湖南", "total": "24.2 ", "index_score": "23.2 "}
{"ranking": "492", "school": "安徽科技学院", "local": "安徽", "total": "24.1 ", "index_score": "20.1 "}
{"ranking": "492", "school": "滁州学院", "local": "安徽", "total": "24.1 ", "index_score": "22.0 "}
{"ranking": "492", "school": "平顶山学院", "local": "河南", "total": "24.1 ", "index_score": "26.9 "}
{"ranking": "492", "school": "四川文理学院", "local": "四川", "total": "24.1 ", "index_score": "17.8 "}
{"ranking": "492", "school": "泰山学院", "local": "山东", "total": "24.1 ", "index_score": "15.9 "}
{"ranking": "492", "school": "浙江万里学院", "local": "浙江", "total": "24.1 ", "index_score": "15.7 "}
{"ranking": "498", "school": "滨州学院", "local": "山东", "total": "24.0 ", "index_score": "16.2 "}
{"ranking": "498", "school": "天津职业技术师范大学", "local": "天津", "total": "24.0 ", "index_score": "31.1 "}
{"ranking": "500", "school": "邵阳学院", "local": "湖南", "total": "23.9 ", "index_score": "23.8 "}
